Workbook

Sheet Cover
B2: GLOBAL INVESTMENT SOCIETY | INVESTMENT RESEARCH DIVISION
B4: lululemon athletica inc. (NASDAQ: LULU)
B5: Integrated Three-Statement Operating Model
B7: Historical figures (FY2022–FY2025) per company SEC filings (Form 10-K).
B8: Fiscal year ends late January / early February; FY2025 ended February 1, 2026.
B10: FONT / COLOR CONVENTION
B11: Blue font = figures reported by the company (click value or 10-K link for source)
B12: Black font = calculations / formulas
B13: Red font = analyst assumptions — cols B/C/D on every tab: Justification | Source | Ctrl+F
B15: SOURCES
B16: SEC EDGAR filings, CIK 0001397187 (Forms 10-K) Ctrl+F: Ctrl+F "10-K" → FY2025 accession 0001397187-26-000020
B17: FY2025 Form 10-K (ended Feb 1, 2026) Ctrl+F: Ctrl+F "Net revenue" → 11,102,600 or "Depreciation and amortization" → 496,228 on this 10-K HTML file
... B25: Built from scratch for the GIS IR selection assignment. Units: US$ thousands unless noted.

Sheet Assumptions
A1: OPERATING ASSUMPTIONS & DRIVERS | E1: FY2022 | F1: FY2023 | G1: FY2024 | H1: FY2025 | I1: FY2026E | J1: FY2027E | K1: FY2028E | L1: FY2029E | M1: FY2030E
B2: Justification (~20 words) | C2: Source (click) | D2: Ctrl+F (prove number) | E2: Jan 29, 2023 | F2: Jan 28, 2024 | G2: Feb 2, 2025 | H2: Feb 1, 2026 | I2: proj. | J2: proj. | K2: proj. | L2: proj. | M2: proj.
A4: GROWTH & MARGINS
A5: Revenue growth % | B5: FY26 −6.1% is guidance midpoint. FY27 +2.6% then +2.3% tracks StockAnalysis next-year +2.64% and 3Y forecast 2.26%. | C5: StockAnalysis: LULU revenue forecast (FY27–30) | D5: FY26: earnings release Ctrl+F "decline of 5% to 7%". FY27–30: this page Ctrl+F "Revenue Growth Forecast (3Y)" → 2.26%. Model 2.3%. | F5: 0.18602511 | G5: 0.10071941 | H5: 0.048589713 | I5: -0.061 | J5: 0.026 | K5: 0.023 | L5: 0.023 | M5: 0.023
A6: Gross margin % (clean, ex-refunds) | B6: Clean GM 56.5%→58.0% (ex-refunds), still below peak ~58–59%. FY26 COGS is then reduced by the $134.5M IEEPA refund. | C6: LULU historical gross margin (10-K) | D6: Ctrl+F "Gross profit" → 6,284,132 ÷ "Net revenue" 11,102,600 = 56.6% FY25 anchor | E6: 0.55389064 | F6: 0.583142 | G6: 0.59224937 | H6: 0.56600544 | I6: 0.565 | J6: 0.57 | K6: 0.575 | L6: 0.575 | M6: 0.58
A7: IEEPA tariff refunds ($k, FY26 only) | B7: Add back $134.5M in FY26 only — already recognized (reduced COGS). +130bps on FY26 sales, not +560bps (that was Q2-only). | C7: Q2 FY2026 release: $134.5M IEEPA tariff refunds | D7: Ctrl+F "134.5 million" → IEEPA tariff refunds reduced COGS. Add this dollar amount to FY26 EBIT only. Full-year boost = 134.5 / FY26 sales ≈ 1.3ppt, not 5.6ppt. | E7: 0 | F7: 0 | G7: 0 | H7: 0 | I7: 134500 | J7: 0 | K7: 0 | L7: 0 | M7: 0
A8: SG&A % of revenue | B8: FY26 SG&A 42.5% matches YTD 42.3% (earnings), vs FY25 36.7% 10-K; then fades to 39.5% as volume stabilizes. | C8: LULU Q2 FY2026 earnings release (YTD SG&A %) | D8: Ctrl+F "41.7%" (Q2 SG&A % of net revenue) and "42.3%" (first two quarters). FY25 10-K is 36.7%. Model FY26 42.5% | E8: 0.33998408 | F8: 0.35316767 | G8: 0.35533946 | H8: 0.3662706 | I8: 0.425 | J8: 0.415 | K8: 0.405 | L8: 0.4 | M8: 0.395
A9: Amortization / other opex ($) | B9: $7M annual amortization run-rate; stable intangible amortization per recent 10-K disclosure levels. | C9: LULU FY2025 10-K | D9: Ctrl+F "Amortization of intangible assets" → 6,961 ($000); model $7,000/yr | E9: 406485 | F9: 79511 | G9: 2735 | H9: 6961 | I9: 7000 | J9: 7000 | K9: 7000 | L9: 7000 | M9: 7000
A10: Other income, net ($) | B10: FY26 $45M other income annualizes YTD $22,829; then steps down as cash is deployed (FY25 was only $28,352). | C10: Q2 FY2026 YTD other income (earnings) | D10: Ctrl+F "22,829" → YTD other income ($000) on the earnings P&L. FY26 model $45,000 annualizes that run-rate. | E10: 4163 | F10: 43059 | G10: 70380 | H10: 28352 | I10: 45000 | J10: 40000 | K10: 35000 | L10: 30000 | M10: 25000
A11: Effective tax rate % | B11: 30% effective tax rate on projections; conservative vs recent ~29% effective, allows for jurisdictional mix. | C11: LULU Q2 FY2026 outlook (≈30% tax) | D11: Ctrl+F "a tax rate of approximately 30%" on the earnings outlook; FY25 10-K 29.5%. 3-statement model 30% | E11: 0.35853324 | F11: 0.28750974 | G11: 0.29558938 | H11: 0.29468232 | I11: 0.3 | J11: 0.3 | K11: 0.3 | L11: 0.3 | M11: 0.3
A12: CAPITAL & NON-CASH ITEMS
A13: D&A % of revenue | B13: D&A 4.5–4.6% of revenue; tracks recent depreciation intensity on PPE and lease-related amortization. | C13: LULU CF statement (10-K) | D13: Ctrl+F "Depreciation and amortization" → 496,228 ÷ "Net revenue" 11,102,600 = 4.5% | E13: 0.035976864 | F13: 0.039439966 | G13: 0.042172146 | H13: 0.044694756 | I13: 0.046 | J13: 0.046 | K13: 0.045 | L13: 0.045 | M13: 0.045
A14: Capex % of revenue | B14: FY26 7.0% is $735M / $10.4B, not / FY25 $11.1B. Since 7.0% steps toward FY25 6.1%, we assume a fade: 7.0 / 6.0 / 5.5 / 5.0 / 5.0. Also: FY26 sales are $10.35–$10.50B (earnings). Use that $10.4B year as the 7% denominator, not FY25 $11.1B. | C14: LULU CF statement (10-K) Also: Q2 FY2026 outlook: $10.350B–$10.500B sales | D14: FY25 actual (10-K) Ctrl+F "680,802" → capex $680.8M Ctrl+F "11,102,600" → sales $11.1B 680.8 / 11,102.6 = 6.1% FY26 capex (10-K) Ctrl+F "$725.0 million and $745.0 million" → mid $735M FY26 sales (earnings) Ctrl+F "$10.350 billion to $10.500 billion" → $10.35–$10.50B (mid $10.425B) 7.0% = $735M / $10.425B ($10B year, not FY25 $11.1B) DCF blend Fade 7.0 / 6.0 / 5.5 / 5.0 / 4.0 5.5% = (7.0+6.0+5.5+5.0+4.0)/5 | E14: 0.078744292 | F14: 0.067766521 | G14: 0.065094805 | H14: 0.06131915 | I14: 0.07 | J14: 0.06 | K14: 0.055 | L14: 0.05 | M14: 0.05
A15: Stock-based compensation ($) | B15: $62M SBC holds the FY25 10-K run-rate (Stock-based compensation expense 62,203). | C15: LULU CF statement (10-K) | D15: Ctrl+F "Stock-based compensation expense" → 62,203 on this 10-K HTML. Model $62,000. | E15: 78075 | F15: 93560 | G15: 90011 | H15: 62203 | I15: 62000 | J15: 62000 | K15: 62000 | L15: 62000 | M15: 62000
A16: WORKING CAPITAL & BALANCE SHEET DRIVERS
A17: Inventories % of COGS | B17: Inventory 33–34% of COGS; slight normalization from FY25 build as Americas demand softens and clears. | C17: LULU balance sheet (10-K) | D17: Ctrl+F "Inventories" → 1,700,753 ÷ "Cost of goods sold" 4,818,468 = 35.3% | E17: 0.40002648 | F17: 0.33008577 | G17: 0.33402265 | H17: 0.35296551 | I17: 0.34 | J17: 0.335 | K17: 0.33 | L17: 0.33 | M17: 0.33
A18: Accounts receivable % of revenue | B18: AR 1.7% of sales = FY25 Accounts receivable, net 190,657 / 11,102,600. Wholesale and marketplace receivables; hold the FY25 mix. | C18: LULU FY2025 10-K: Accounts receivable, net | D18: Ctrl+F "Accounts receivable, net" (one hit on the BS) → 190,657 ($000). 190,657 / 11,102,600 = 1.7% of sales. Model holds 1.7%. | E18: 0.016386869 | F18: 0.012970724 | G18: 0.011349789 | H18: 0.017172284 | I18: 0.017 | J18: 0.017 | K18: 0.017 | L18: 0.017 | M18: 0.017
A19: Accounts payable % of COGS | B19: AP 6.8% of COGS; holds near FY25 level reflecting vendor terms and production payment cadence. | C19: LULU balance sheet (10-K) | D19: Ctrl+F "Accounts payable" → 331,421 ÷ "Cost of goods sold" 4,818,468 = 6.9% | E19: 0.04774005 | F19: 0.08689577 | G19: 0.062864535 | H19: 0.068781405 | I19: 0.068 | J19: 0.068 | K19: 0.068 | L19: 0.068 | M19: 0.068
A20: Accrued liabilities % of revenue | B20: Accrued liabilities 5.8% of revenue; stable comp, marketing, and operating accrual ratio. | C20: LULU balance sheet (10-K) | D20: Ctrl+F "Accrued liabilities and other" → 662,982 ÷ "Net revenue" 11,102,600 = 6.0% | E20: 0.049222873 | F20: 0.036235048 | G20: 0.052838718 | H20: 0.059714121 | I20: 0.058 | J20: 0.058 | K20: 0.058 | L20: 0.058 | M20: 0.058
A21: Other current assets % of revenue | B21: OCA 5.1% is current assets minus cash, AR, and inventory (prepaids / tax receivables). AR is its own line, not inside OCA. | C21: LULU balance sheet (10-K) | D21: OCA = "Total current assets" 4,262,701 − cash 1,807,202 − "Accounts receivable, net" 190,657 − "Inventories" 1,700,753 = 564,089 (5.1% of sales). AR is not inside this residual. | E21: 0.052316387 | F21: 0.03828094 | G21: 0.040962112 | H21: 0.050806928 | I21: 0.051 | J21: 0.051 | K21: 0.051 | L21: 0.051 | M21: 0.051
A22: Operating lease ROU asset % of revenue | B22: ROU assets 14.7% of revenue; lease-intensive store model, stable vs FY25 operating lease footprint. | C22: LULU lease disclosures (10-K) | D22: Ctrl+F "Right-of-use lease assets" → 1,630,181 ÷ "Net revenue" 11,102,600 = 14.7% | E22: 0.11952615 | F22: 0.13157017 | G22: 0.13375889 | H22: 0.14682876 | I22: 0.147 | J22: 0.147 | K22: 0.147 | L22: 0.147 | M22: 0.147
A23: Other non-current assets % of revenue | B23: ONCA 3.0% = FY25 total assets − CA − PPE − ROU − GW (338,947); matches earnings 'deferred taxes and other NC assets'. | C23: LULU balance sheet (10-K) | D23: Ctrl+F "Total assets" 8,456,743 − current assets − "Property and equipment, net" − "Right-of-use lease assets" − goodwill/intangibles = 338,947 (3.0%) | E23: 0.020029177 | F23: 0.020361196 | G23: 0.024076593 | H23: 0.030528615 | I23: 0.03 | J23: 0.03 | K23: 0.03 | L23: 0.03 | M23: 0.03
A24: Op lease liab (current) % of revenue | B24: Current lease liabilities 2.7% of revenue; short-term portion of operating lease obligations. | C24: LULU lease disclosures (10-K) | D24: Ctrl+F "Current lease liabilities" → 298,724 ÷ "Net revenue" 11,102,600 = 2.7% | E24: 0.025642259 | F24: 0.025913587 | G24: 0.025987035 | H24: 0.02690577 | I24: 0.027 | J24: 0.027 | K24: 0.027 | L24: 0.027 | M24: 0.027
A25: Op lease liab (non-current) % of revenue | B25: Non-current lease liabilities 13.5% of revenue; long-term store lease commitments per 10-K. | C25: LULU lease disclosures (10-K) | D25: Ctrl+F "Non-current lease liabilities" → 1,499,717 ÷ "Net revenue" 11,102,600 = 13.5% | E25: 0.10632638 | F25: 0.11996867 | G25: 0.12283921 | H25: 0.135078 | I25: 0.135 | J25: 0.135 | K25: 0.135 | L25: 0.135 | M25: 0.135
A26: Other current liabilities % of revenue | B26: OCL 5.5% = FY25 current liabilities minus AP, accrued, and current leases (residual ~594k); not the 45,954 'other' line alone. | C26: LULU balance sheet (10-K) | D26: Ctrl+F "Total current liabilities" 1,887,548 − "Accounts payable" 331,421 − "Accrued liabilities and other" 662,982 − "Current lease liabilities" 298,724 ≈ 594,421 (5.4%) | E26: 0.087820655 | F26: 0.071210646 | G26: 0.069285821 | H26: 0.053538901 | I26: 0.055 | J26: 0.055 | K26: 0.055 | L26: 0.055 | M26: 0.055
A27: Other non-current liab % of revenue | B27: Other non-current liabilities 0.5% of revenue; minor long-term accruals and provisions. | C27: LULU balance sheet (10-K) | D27: Ctrl+F "Other non-current liabilities" → 55,360 ÷ "Net revenue" 11,102,600 = 0.5% | E27: 0.0059916025 | F27: 0.004684863 | G27: 0.0038524287 | H27: 0.0049862194 | I27: 0.005 | J27: 0.005 | K27: 0.005 | L27: 0.005 | M27: 0.005
A28: CAPITAL RETURN
A29: Share repurchases ($) | B29: $500M annual repurchases; continued capital return at moderated pace vs FY24–25 peak buyback levels. | C29: LULU CF: share repurchases (10-K) | D29: Ctrl+F "Repurchase of common stock" → ( 1,178,349 ) ($000) FY25; model (500,000)/yr | E29: 444001 | F29: 558652 | G29: 1636879 | H29: 1178349 | I29: 500000 | J29: 500000 | K29: 500000 | L29: 500000 | M29: 500000
A30: Avg repurchase price ($/sh) | B30: FY26 repurchase price $100 matches the current quote; path $100→$130 is a recovery assumption (FY25 10-K paid $168–$199). | C30: NASDAQ LULU last sale (current price) | D30: Ctrl+F "LULU" → Last Sale / Previous Close (~$100). FY26 model repurchase price starts at $100. | I30: 100 | J30: 108 | K30: 115 | L30: 122 | M30: 130
A32: Historical columns = derived ratios (black); projection columns = analyst inputs (red).

Sheet Income Statement
A1: INCOME STATEMENT (US$ thousands) | E1: FY2022 | F1: FY2023 | G1: FY2024 | H1: FY2025 | I1: FY2026E | J1: FY2027E | K1: FY2028E | L1: FY2029E | M1: FY2030E
B2: Justification (~20 words) | C2: Source (click) | D2: Ctrl+F (prove number) | E2: 10-K | F2: 10-K | G2: 10-K | H2: 10-K | I2: Projected
A4: Net revenue | B4: FY26 −6.1% is guidance midpoint. FY27 +2.6% then +2.3% tracks StockAnalysis next-year +2.64% and 3Y forecast 2.26%. | C4: StockAnalysis: LULU revenue forecast (FY27–30) | D4: FY26: earnings release Ctrl+F "decline of 5% to 7%". FY27–30: this page Ctrl+F "Revenue Growth Forecast (3Y)" → 2.26%. Model 2.3%. | E4: 8110518 | F4: 9619278 | G4: 10588126 | H4: 11102600 | I4: =H4*(1+'Assumptions'!I5) | J4: =I4*(1+'Assumptions'!J5) | K4: =J4*(1+'Assumptions'!K5) | L4: =K4*(1+'Assumptions'!L5) | M4: =L4*(1+'Assumptions'!M5)
A5: Cost of goods sold (ex-refunds) | B5: Clean GM 56.5%→58.0% (ex-refunds), still below peak ~58–59%. FY26 COGS is then reduced by the $134.5M IEEPA refund. | C5: LULU historical gross margin (10-K) | D5: Ctrl+F "Gross profit" → 6,284,132 ÷ "Net revenue" 11,102,600 = 56.6% FY25 anchor | E5: 3618178 | F5: 4009873 | G5: 4317315 | H5: 4818468 | I5: =I4*(1-'Assumptions'!I6) | J5: =J4*(1-'Assumptions'!J6) | K5: =K4*(1-'Assumptions'!K6) | L5: =L4*(1-'Assumptions'!L6) | M5: =M4*(1-'Assumptions'!M6)
A6: Less: IEEPA tariff refunds (FY26 only) | B6: Add back $134.5M in FY26 only — already recognized (reduced COGS). +130bps on FY26 sales, not +560bps (that was Q2-only). | C6: Q2 FY2026 release: $134.5M IEEPA tariff refunds | D6: Ctrl+F "134.5 million" → IEEPA tariff refunds reduced COGS. Add this dollar amount to FY26 EBIT only. Full-year boost = 134.5 / FY26 sales ≈ 1.3ppt, not 5.6ppt. | E6: 0 | F6: 0 | G6: 0 | H6: 0 | I6: =-'Assumptions'!I7 | J6: =-'Assumptions'!J7 | K6: =-'Assumptions'!K7 | L6: =-'Assumptions'!L7 | M6: =-'Assumptions'!M7
A7: Gross profit | E7: =E4-E5-E6 | F7: =F4-F5-F6 | G7: =G4-G5-G6 | H7: =H4-H5-H6 | I7: =I4-I5-I6 | J7: =J4-J5-J6 | K7: =K4-K5-K6 | L7: =L4-L5-L6 | M7: =M4-M5-M6
A8: Selling, general & administrative | B8: FY26 SG&A 42.5% matches YTD 42.3% (earnings), vs FY25 36.7% 10-K; then fades to 39.5% as volume stabilizes. | C8: LULU Q2 FY2026 earnings release (YTD SG&A %) | D8: Ctrl+F "41.7%" (Q2 SG&A % of net revenue) and "42.3%" (first two quarters). FY25 10-K is 36.7%. Model FY26 42.5% | E8: 2757447 | F8: 3397218 | G8: 3762379 | H8: 4066556 | I8: =I4*'Assumptions'!I8 | J8: =J4*'Assumptions'!J8 | K8: =K4*'Assumptions'!K8 | L8: =L4*'Assumptions'!L8 | M8: =M4*'Assumptions'!M8
A9: Amortization of intangibles / other | B9: $7M annual amortization run-rate; stable intangible amortization per recent 10-K disclosure levels. | C9: LULU FY2025 10-K | D9: Ctrl+F "Amortization of intangible assets" → 6,961 ($000); model $7,000/yr | E9: 406485 | F9: 79511 | G9: 2735 | H9: 6961 | I9: ='Assumptions'!I9 | J9: ='Assumptions'!J9 | K9: ='Assumptions'!K9 | L9: ='Assumptions'!L9 | M9: ='Assumptions'!M9
A10: Operating income (EBIT) | E10: =E7-E8-E9 | F10: =F7-F8-F9 | G10: =G7-G8-G9 | H10: =H7-H8-H9 | I10: =I7-I8-I9 | J10: =J7-J8-J9 | K10: =K7-K8-K9 | L10: =L7-L8-L9 | M10: =M7-M8-M9
A11: Other income, net | B11: FY26 $45M other income annualizes YTD $22,829; then steps down as cash is deployed (FY25 was only $28,352). | C11: Q2 FY2026 YTD other income (earnings) | D11: Ctrl+F "22,829" → YTD other income ($000) on the earnings P&L. FY26 model $45,000 annualizes that run-rate. | E11: 4163 | F11: 43059 | G11: 70380 | H11: 28352 | I11: ='Assumptions'!I10 | J11: ='Assumptions'!J10 | K11: ='Assumptions'!K10 | L11: ='Assumptions'!L10 | M11: ='Assumptions'!M10
A12: Pre-tax income | E12: =E10+E11 | F12: =F10+F11 | G12: =G10+G11 | H12: =H10+H11 | I12: =I10+I11 | J12: =J10+J11 | K12: =K10+K11 | L12: =L10+L11 | M12: =M10+M11
A13: Income tax expense | B13: 30% effective tax rate on projections; conservative vs recent ~29% effective, allows for jurisdictional mix. | C13: LULU Q2 FY2026 outlook (≈30% tax) | D13: Ctrl+F "a tax rate of approximately 30%" on the earnings outlook; FY25 10-K 29.5%. 3-statement model 30% | E13: 477771 | F13: 625545 | G13: 761461 | H13: 659784 | I13: =I12*'Assumptions'!I11 | J13: =J12*'Assumptions'!J11 | K13: =K12*'Assumptions'!K11 | L13: =L12*'Assumptions'!L11 | M13: =M12*'Assumptions'!M11
A14: Net income | E14: =E12-E13 | F14: =F12-F13 | G14: =G12-G13 | H14: =H12-H13 | I14: =I12-I13 | J14: =J12-J13 | K14: =K12-K13 | L14: =L12-L13 | M14: =M12-M13
A16: Diluted weighted-avg shares (000) | B16: $500M annual repurchases; continued capital return at moderated pace vs FY24–25 peak buyback levels. Also: FY26 repurchase price $100 matches the current quote; path $100→$130 is a recovery assumption (FY25 10-K paid $168–$199). | C16: LULU CF: share repurchases (10-K) Also: NASDAQ LULU last sale (current price) | D16: Ctrl+F "Repurchase of common stock" → ( 1,178,349 ) ($000) FY25; model (500,000)/yr Also: Ctrl+F "LULU" → Last Sale / Previous Close (~$100). FY26 model repurchase price starts at $100. | E16: 128017 | F16: 127060 | G16: 123935 | H16: 119068 | I16: =H16-'Assumptions'!I29/'Assumptions'!I30 | J16: =I16-'Assumptions'!J29/'Assumptions'!J30 | K16: =J16-'Assumptions'!K29/'Assumptions'!K30 | L16: =K16-'Assumptions'!L29/'Assumptions'!L30 | M16: =L16-'Assumptions'!M29/'Assumptions'!M30
A17: Diluted EPS ($) | E17: 6.68 | F17: 12.2 | G17: 14.64 | H17: 13.26 | I17: =I14/I16 | J17: =J14/J16 | K17: =K14/K16 | L17: =L14/L16 | M17: =M14/M16
A19: Margins & growth
A20: Gross margin % | E20: =E7/E4 | F20: =F7/F4 | G20: =G7/G4 | H20: =H7/H4 | I20: =I7/I4 | J20: =J7/J4 | K20: =K7/K4 | L20: =L7/L4 | M20: =M7/M4
A21: Clean operating margin % (ex-refunds) | E21: =(E10+E6)/E4 | F21: =(F10+F6)/F4 | G21: =(G10+G6)/G4 | H21: =(H10+H6)/H4 | I21: =(I10+I6)/I4 | J21: =(J10+J6)/J4 | K21: =(K10+K6)/K4 | L21: =(L10+L6)/L4 | M21: =(M10+M6)/M4
A22: Operating margin % (reported, incl. FY26 refund) | E22: =E10/E4 | F22: =F10/F4 | G22: =G10/G4 | H22: =H10/H4 | I22: =I10/I4 | J22: =J10/J4 | K22: =K10/K4 | L22: =L10/L4 | M22: =M10/M4
A23: Net margin % | E23: =E14/E4 | F23: =F14/F4 | G23: =G14/G4 | H23: =H14/H4 | I23: =I14/I4 | J23: =J14/J4 | K23: =K14/K4 | L23: =L14/L4 | M23: =M14/M4
A24: Revenue growth % | E24: n/a | F24: =F4/E4-1 | G24: =G4/F4-1 | H24: =H4/G4-1 | I24: =I4/H4-1 | J24: =J4/I4-1 | K24: =K4/J4-1 | L24: =L4/K4-1 | M24: =M4/L4-1

Sheet Balance Sheet
A1: BALANCE SHEET (US$ thousands) | E1: FY2022 | F1: FY2023 | G1: FY2024 | H1: FY2025 | I1: FY2026E | J1: FY2027E | K1: FY2028E | L1: FY2029E | M1: FY2030E
B2: Justification (~20 words) | C2: Source (click) | D2: Ctrl+F (prove number) | E2: 10-K | F2: 10-K | G2: 10-K | H2: 10-K | I2: Projected
A4: ASSETS
A5: Current assets:
A6: Cash & cash equivalents | E6: 1154867 | F6: 2243971 | G6: 1984336 | H6: 1807202 | I6: ='Cash Flow'!I34 | J6: ='Cash Flow'!J34 | K6: ='Cash Flow'!K34 | L6: ='Cash Flow'!L34 | M6: ='Cash Flow'!M34
A7: Accounts receivable, net | B7: AR 1.7% of sales = FY25 Accounts receivable, net 190,657 / 11,102,600. Wholesale and marketplace receivables; hold the FY25 mix. | C7: LULU FY2025 10-K: Accounts receivable, net | D7: Ctrl+F "Accounts receivable, net" (one hit on the BS) → 190,657 ($000). 190,657 / 11,102,600 = 1.7% of sales. Model holds 1.7%. | E7: 132906 | F7: 124769 | G7: 120173 | H7: 190657 | I7: ='Income Statement'!I4*'Assumptions'!I18 | J7: ='Income Statement'!J4*'Assumptions'!J18 | K7: ='Income Statement'!K4*'Assumptions'!K18 | L7: ='Income Statement'!L4*'Assumptions'!L18 | M7: ='Income Statement'!M4*'Assumptions'!M18
A8: Inventories | B8: Inventory 33–34% of COGS; slight normalization from FY25 build as Americas demand softens and clears. | C8: LULU balance sheet (10-K) | D8: Ctrl+F "Inventories" → 1,700,753 ÷ "Cost of goods sold" 4,818,468 = 35.3% | E8: 1447367 | F8: 1323602 | G8: 1442081 | H8: 1700753 | I8: ='Income Statement'!I5*'Assumptions'!I17 | J8: ='Income Statement'!J5*'Assumptions'!J17 | K8: ='Income Statement'!K5*'Assumptions'!K17 | L8: ='Income Statement'!L5*'Assumptions'!L17 | M8: ='Income Statement'!M5*'Assumptions'!M17
A9: Other current assets | B9: OCA 5.1% is current assets minus cash, AR, and inventory (prepaids / tax receivables). AR is its own line, not inside OCA. | C9: LULU balance sheet (10-K) | D9: OCA = "Total current assets" 4,262,701 − cash 1,807,202 − "Accounts receivable, net" 190,657 − "Inventories" 1,700,753 = 564,089 (5.1% of sales). AR is not inside this residual. | E9: 424313 | F9: 368235 | G9: 433712 | H9: 564089 | I9: ='Income Statement'!I4*'Assumptions'!I21 | J9: ='Income Statement'!J4*'Assumptions'!J21 | K9: ='Income Statement'!K4*'Assumptions'!K21 | L9: ='Income Statement'!L4*'Assumptions'!L21 | M9: ='Income Statement'!M4*'Assumptions'!M21
A10: Total current assets | E10: 3159453 | F10: 4060577 | G10: 3980302 | H10: 4262701 | I10: =I6+I7+I8+I9 | J10: =J6+J7+J8+J9 | K10: =K6+K7+K8+K9 | L10: =L6+L7+L8+L9 | M10: =M6+M7+M8+M9
A11: Non-current assets:
A12: Property & equipment, net | B12: FY26 7.0% is $735M / $10.4B, not / FY25 $11.1B. Since 7.0% steps toward FY25 6.1%, we assume a fade: 7.0 / 6.0 / 5.5 / 5.0 / 5.0. | C12: LULU CF statement (10-K) | D12: FY25 actual (10-K) Ctrl+F "680,802" → capex $680.8M Ctrl+F "11,102,600" → sales $11.1B 680.8 / 11,102.6 = 6.1% FY26 capex (10-K) Ctrl+F "$725.0 million and $745.0 million" → mid $735M FY26 sales (earnings) Ctrl+F "$10.350 billion to $10.500 billion" → $10.35–$10.50B (mid $10.425B) 7.0% = $735M / $10.425B ($10B year, not FY25 $11.1B) DCF blend Fade 7.0 / 6.0 / 5.5 / 5.0 / 4.0 5.5% = (7.0+6.0+5.5+5.0+4.0)/5 | E12: 1269614 | F12: 1545811 | G12: 1780617 | H12: 2033720 | I12: =H12+'Income Statement'!I4*'Assumptions'!I14-'Income Statement'!I4*'Assumptions'!I13 | J12: =I12+'Income Statement'!J4*'Assumptions'!J14-'Income Statement'!J4*'Assumptions'!J13 | K12: =J12+'Income Statement'!K4*'Assumptions'!K14-'Income Statement'!K4*'Assumptions'!K13 | L12: =K12+'Income Statement'!L4*'Assumptions'!L14-'Income Statement'!L4*'Assumptions'!L13 | M12: =L12+'Income Statement'!M4*'Assumptions'!M14-'Income Statement'!M4*'Assumptions'!M13
A13: Operating lease right-of-use assets | B13: ROU assets 14.7% of revenue; lease-intensive store model, stable vs FY25 operating lease footprint. | C13: LULU lease disclosures (10-K) | D13: Ctrl+F "Right-of-use lease assets" → 1,630,181 ÷ "Net revenue" 11,102,600 = 14.7% | E13: 969419 | F13: 1265610 | G13: 1416256 | H13: 1630181 | I13: ='Income Statement'!I4*'Assumptions'!I22 | J13: ='Income Statement'!J4*'Assumptions'!J22 | K13: ='Income Statement'!K4*'Assumptions'!K22 | L13: ='Income Statement'!L4*'Assumptions'!L22 | M13: ='Income Statement'!M4*'Assumptions'!M22
A14: Goodwill & intangible assets | E14: 46105 | F14: 24083 | G14: 171191 | H14: 191194 | I14: =H14 | J14: =I14 | K14: =J14 | L14: =K14 | M14: =L14
A15: Other non-current assets | B15: ONCA 3.0% = FY25 total assets − CA − PPE − ROU − GW (338,947); matches earnings 'deferred taxes and other NC assets'. | C15: LULU balance sheet (10-K) | D15: Ctrl+F "Total assets" 8,456,743 − current assets − "Property and equipment, net" − "Right-of-use lease assets" − goodwill/intangibles = 338,947 (3.0%) | E15: 162447 | F15: 195860 | G15: 254926 | H15: 338947 | I15: ='Income Statement'!I4*'Assumptions'!I23 | J15: ='Income Statement'!J4*'Assumptions'!J23 | K15: ='Income Statement'!K4*'Assumptions'!K23 | L15: ='Income Statement'!L4*'Assumptions'!L23 | M15: ='Income Statement'!M4*'Assumptions'!M23
A16: TOTAL ASSETS | E16: 5607038 | F16: 7091941 | G16: 7603292 | H16: 8456743 | I16: =I10+I12+I13+I14+I15 | J16: =J10+J12+J13+J14+J15 | K16: =K10+K12+K13+K14+K15 | L16: =L10+L12+L13+L14+L15 | M16: =M10+M12+M13+M14+M15
A18: LIABILITIES & EQUITY
A19: Current liabilities:
A20: Accounts payable | B20: AP 6.8% of COGS; holds near FY25 level reflecting vendor terms and production payment cadence. | C20: LULU balance sheet (10-K) | D20: Ctrl+F "Accounts payable" → 331,421 ÷ "Cost of goods sold" 4,818,468 = 6.9% | E20: 172732 | F20: 348441 | G20: 271406 | H20: 331421 | I20: ='Income Statement'!I5*'Assumptions'!I19 | J20: ='Income Statement'!J5*'Assumptions'!J19 | K20: ='Income Statement'!K5*'Assumptions'!K19 | L20: ='Income Statement'!L5*'Assumptions'!L19 | M20: ='Income Statement'!M5*'Assumptions'!M19
A21: Accrued liabilities | B21: Accrued liabilities 5.8% of revenue; stable comp, marketing, and operating accrual ratio. | C21: LULU balance sheet (10-K) | D21: Ctrl+F "Accrued liabilities and other" → 662,982 ÷ "Net revenue" 11,102,600 = 6.0% | E21: 399223 | F21: 348555 | G21: 559463 | H21: 662982 | I21: ='Income Statement'!I4*'Assumptions'!I20 | J21: ='Income Statement'!J4*'Assumptions'!J20 | K21: ='Income Statement'!K4*'Assumptions'!K20 | L21: ='Income Statement'!L4*'Assumptions'!L20 | M21: ='Income Statement'!M4*'Assumptions'!M20
A22: Operating lease liabilities (current) | B22: Current lease liabilities 2.7% of revenue; short-term portion of operating lease obligations. | C22: LULU lease disclosures (10-K) | D22: Ctrl+F "Current lease liabilities" → 298,724 ÷ "Net revenue" 11,102,600 = 2.7% | E22: 207972 | F22: 249270 | G22: 275154 | H22: 298724 | I22: ='Income Statement'!I4*'Assumptions'!I24 | J22: ='Income Statement'!J4*'Assumptions'!J24 | K22: ='Income Statement'!K4*'Assumptions'!K24 | L22: ='Income Statement'!L4*'Assumptions'!L24 | M22: ='Income Statement'!M4*'Assumptions'!M24
A23: Other current liabilities | B23: OCL 5.5% = FY25 current liabilities minus AP, accrued, and current leases (residual ~594k); not the 45,954 'other' line alone. | C23: LULU balance sheet (10-K) | D23: Ctrl+F "Total current liabilities" 1,887,548 − "Accounts payable" 331,421 − "Accrued liabilities and other" 662,982 − "Current lease liabilities" 298,724 ≈ 594,421 (5.4%) | E23: 712271 | F23: 684995 | G23: 733607 | H23: 594421 | I23: ='Income Statement'!I4*'Assumptions'!I26 | J23: ='Income Statement'!J4*'Assumptions'!J26 | K23: ='Income Statement'!K4*'Assumptions'!K26 | L23: ='Income Statement'!L4*'Assumptions'!L26 | M23: ='Income Statement'!M4*'Assumptions'!M26
A24: Total current liabilities | E24: 1492198 | F24: 1631261 | G24: 1839630 | H24: 1887548 | I24: =I20+I21+I22+I23 | J24: =J20+J21+J22+J23 | K24: =K20+K21+K22+K23 | L24: =L20+L21+L22+L23 | M24: =M20+M21+M22+M23
A25: Non-current liabilities:
A26: Operating lease liabilities (non-current) | B26: Non-current lease liabilities 13.5% of revenue; long-term store lease commitments per 10-K. | C26: LULU lease disclosures (10-K) | D26: Ctrl+F "Non-current lease liabilities" → 1,499,717 ÷ "Net revenue" 11,102,600 = 13.5% | E26: 862362 | F26: 1154012 | G26: 1300637 | H26: 1499717 | I26: ='Income Statement'!I4*'Assumptions'!I25 | J26: ='Income Statement'!J4*'Assumptions'!J25 | K26: ='Income Statement'!K4*'Assumptions'!K25 | L26: ='Income Statement'!L4*'Assumptions'!L25 | M26: ='Income Statement'!M4*'Assumptions'!M25
A27: Deferred income taxes | E27: 55084 | F27: 29522 | G27: 98188 | H27: 52278 | I27: =H27 | J27: =I27 | K27: =J27 | L27: =K27 | M27: =L27
A28: Other non-current liabilities | B28: Other non-current liabilities 0.5% of revenue; minor long-term accruals and provisions. | C28: LULU balance sheet (10-K) | D28: Ctrl+F "Other non-current liabilities" → 55,360 ÷ "Net revenue" 11,102,600 = 0.5% | E28: 48595 | F28: 45065 | G28: 40790 | H28: 55360 | I28: ='Income Statement'!I4*'Assumptions'!I27 | J28: ='Income Statement'!J4*'Assumptions'!J27 | K28: ='Income Statement'!K4*'Assumptions'!K27 | L28: ='Income Statement'!L4*'Assumptions'!L27 | M28: ='Income Statement'!M4*'Assumptions'!M27
A29: TOTAL LIABILITIES | E29: 2458239 | F29: 2859860 | G29: 3279245 | H29: 3494903 | I29: =I24+I26+I27+I28 | J29: =J24+J26+J27+J28 | K29: =K24+K26+K27+K28 | L29: =L24+L26+L27+L28 | M29: =M24+M26+M27+M28
A31: Shareholders' equity:
A32: Common stock & additional paid-in capital | B32: $62M SBC holds the FY25 10-K run-rate (Stock-based compensation expense 62,203). | C32: LULU CF statement (10-K) | D32: Ctrl+F "Stock-based compensation expense" → 62,203 on this 10-K HTML. Model $62,000. | E32: 475256 | F32: 575975 | G32: 638771 | H32: 669949 | I32: =H32+'Assumptions'!I15 | J32: =I32+'Assumptions'!J15 | K32: =J32+'Assumptions'!K15 | L32: =K32+'Assumptions'!L15 | M32: =L32+'Assumptions'!M15
A33: Retained earnings | B33: $500M annual repurchases; continued capital return at moderated pace vs FY24–25 peak buyback levels. | C33: LULU CF: share repurchases (10-K) | D33: Ctrl+F "Repurchase of common stock" → ( 1,178,349 ) ($000) FY25; model (500,000)/yr | E33: 2926127 | F33: 3920362 | G33: 4109717 | H33: 4522581 | I33: =H33+'Income Statement'!I14-'Assumptions'!I29 | J33: =I33+'Income Statement'!J14-'Assumptions'!J29 | K33: =J33+'Income Statement'!K14-'Assumptions'!K29 | L33: =K33+'Income Statement'!L14-'Assumptions'!L29 | M33: =L33+'Income Statement'!M14-'Assumptions'!M29
A34: Accumulated other comprehensive loss | E34: -252584 | F34: -264256 | G34: -424441 | H34: -230690 | I34: =H34 | J34: =I34 | K34: =J34 | L34: =K34 | M34: =L34
A35: TOTAL SHAREHOLDERS' EQUITY | E35: 3148799 | F35: 4232081 | G35: 4324047 | H35: 4961840 | I35: =I32+I33+I34 | J35: =J32+J33+J34 | K35: =K32+K33+K34 | L35: =L32+L33+L34 | M35: =M32+M33+M34
A36: TOTAL LIABILITIES & EQUITY | E36: =E29+E35 | F36: =F29+F35 | G36: =G29+G35 | H36: =H29+H35 | I36: =I29+I35 | J36: =J29+J35 | K36: =K29+K35 | L36: =L29+L35 | M36: =M29+M35
A38: Balance check (Assets − L&E) | E38: =E16-E36 | F38: =F16-F36 | G38: =G16-G36 | H38: =H16-H36 | I38: =I16-I36 | J38: =J16-J36 | K38: =K16-K36 | L38: =L16-L36 | M38: =M16-M36

Sheet Cash Flow
A1: CASH FLOW STATEMENT (US$ thousands) | E1: FY2022 | F1: FY2023 | G1: FY2024 | H1: FY2025 | I1: FY2026E | J1: FY2027E | K1: FY2028E | L1: FY2029E | M1: FY2030E
B2: Justification (~20 words) | C2: Source (click) | D2: Ctrl+F (prove number) | E2: 10-K | F2: 10-K | G2: 10-K | H2: 10-K | I2: Projected
A4: OPERATING ACTIVITIES
A5: Net income | E5: 854800 | F5: 1550190 | G5: 1814616 | H5: 1579183 | I5: ='Income Statement'!I14 | J5: ='Income Statement'!J14 | K5: ='Income Statement'!K14 | L5: ='Income Statement'!L14 | M5: ='Income Statement'!M14
A6: Depreciation & amortization | B6: D&A 4.5–4.6% of revenue; tracks recent depreciation intensity on PPE and lease-related amortization. | C6: LULU CF statement (10-K) | D6: Ctrl+F "Depreciation and amortization" → 496,228 ÷ "Net revenue" 11,102,600 = 4.5% | E6: 291791 | F6: 379384 | G6: 446524 | H6: 496228 | I6: ='Income Statement'!I4*'Assumptions'!I13 | J6: ='Income Statement'!J4*'Assumptions'!J13 | K6: ='Income Statement'!K4*'Assumptions'!K13 | L6: ='Income Statement'!L4*'Assumptions'!L13 | M6: ='Income Statement'!M4*'Assumptions'!M13
A7: Stock-based compensation | B7: $62M SBC holds the FY25 10-K run-rate (Stock-based compensation expense 62,203). | C7: LULU CF statement (10-K) | D7: Ctrl+F "Stock-based compensation expense" → 62,203 on this 10-K HTML. Model $62,000. | E7: 78075 | F7: 93560 | G7: 90011 | H7: 62203 | I7: ='Assumptions'!I15 | J7: ='Assumptions'!J15 | K7: ='Assumptions'!K15 | L7: ='Assumptions'!L15 | M7: ='Assumptions'!M15
A8: (Incr.)/decr. in accounts receivable | B8: AR 1.7% of sales = FY25 Accounts receivable, net 190,657 / 11,102,600. Wholesale and marketplace receivables; hold the FY25 mix. | C8: LULU FY2025 10-K: Accounts receivable, net | D8: Ctrl+F "Accounts receivable, net" (one hit on the BS) → 190,657 ($000). 190,657 / 11,102,600 = 1.7% of sales. Model holds 1.7%. | E8: — | F8: — | G8: — | H8: — | I8: =-('Balance Sheet'!I7-'Balance Sheet'!H7) | J8: =-('Balance Sheet'!J7-'Balance Sheet'!I7) | K8: =-('Balance Sheet'!K7-'Balance Sheet'!J7) | L8: =-('Balance Sheet'!L7-'Balance Sheet'!K7) | M8: =-('Balance Sheet'!M7-'Balance Sheet'!L7)
A9: (Incr.)/decr. in inventories | B9: Inventory 33–34% of COGS; slight normalization from FY25 build as Americas demand softens and clears. | C9: LULU balance sheet (10-K) | D9: Ctrl+F "Inventories" → 1,700,753 ÷ "Cost of goods sold" 4,818,468 = 35.3% | E9: — | F9: — | G9: — | H9: — | I9: =-('Balance Sheet'!I8-'Balance Sheet'!H8) | J9: =-('Balance Sheet'!J8-'Balance Sheet'!I8) | K9: =-('Balance Sheet'!K8-'Balance Sheet'!J8) | L9: =-('Balance Sheet'!L8-'Balance Sheet'!K8) | M9: =-('Balance Sheet'!M8-'Balance Sheet'!L8)
A10: (Incr.)/decr. in other current assets | B10: OCA 5.1% is current assets minus cash, AR, and inventory (prepaids / tax receivables). AR is its own line, not inside OCA. | C10: LULU balance sheet (10-K) | D10: OCA = "Total current assets" 4,262,701 − cash 1,807,202 − "Accounts receivable, net" 190,657 − "Inventories" 1,700,753 = 564,089 (5.1% of sales). AR is not inside this residual. | E10: — | F10: — | G10: — | H10: — | I10: =-('Balance Sheet'!I9-'Balance Sheet'!H9) | J10: =-('Balance Sheet'!J9-'Balance Sheet'!I9) | K10: =-('Balance Sheet'!K9-'Balance Sheet'!J9) | L10: =-('Balance Sheet'!L9-'Balance Sheet'!K9) | M10: =-('Balance Sheet'!M9-'Balance Sheet'!L9)
A11: (Incr.)/decr. in ROU assets | B11: ROU assets 14.7% of revenue; lease-intensive store model, stable vs FY25 operating lease footprint. | C11: LULU lease disclosures (10-K) | D11: Ctrl+F "Right-of-use lease assets" → 1,630,181 ÷ "Net revenue" 11,102,600 = 14.7% | E11: — | F11: — | G11: — | H11: — | I11: =-('Balance Sheet'!I13-'Balance Sheet'!H13) | J11: =-('Balance Sheet'!J13-'Balance Sheet'!I13) | K11: =-('Balance Sheet'!K13-'Balance Sheet'!J13) | L11: =-('Balance Sheet'!L13-'Balance Sheet'!K13) | M11: =-('Balance Sheet'!M13-'Balance Sheet'!L13)
A12: (Incr.)/decr. in other non-current assets | B12: ONCA 3.0% = FY25 total assets − CA − PPE − ROU − GW (338,947); matches earnings 'deferred taxes and other NC assets'. | C12: LULU balance sheet (10-K) | D12: Ctrl+F "Total assets" 8,456,743 − current assets − "Property and equipment, net" − "Right-of-use lease assets" − goodwill/intangibles = 338,947 (3.0%) | E12: — | F12: — | G12: — | H12: — | I12: =-('Balance Sheet'!I15-'Balance Sheet'!H15) | J12: =-('Balance Sheet'!J15-'Balance Sheet'!I15) | K12: =-('Balance Sheet'!K15-'Balance Sheet'!J15) | L12: =-('Balance Sheet'!L15-'Balance Sheet'!K15) | M12: =-('Balance Sheet'!M15-'Balance Sheet'!L15)
A13: Incr./(decr.) in accounts payable | B13: AP 6.8% of COGS; holds near FY25 level reflecting vendor terms and production payment cadence. | C13: LULU balance sheet (10-K) | D13: Ctrl+F "Accounts payable" → 331,421 ÷ "Cost of goods sold" 4,818,468 = 6.9% | E13: — | F13: — | G13: — | H13: — | I13: =('Balance Sheet'!I20-'Balance Sheet'!H20) | J13: =('Balance Sheet'!J20-'Balance Sheet'!I20) | K13: =('Balance Sheet'!K20-'Balance Sheet'!J20) | L13: =('Balance Sheet'!L20-'Balance Sheet'!K20) | M13: =('Balance Sheet'!M20-'Balance Sheet'!L20)
A14: Incr./(decr.) in accrued liabilities | B14: Accrued liabilities 5.8% of revenue; stable comp, marketing, and operating accrual ratio. | C14: LULU balance sheet (10-K) | D14: Ctrl+F "Accrued liabilities and other" → 662,982 ÷ "Net revenue" 11,102,600 = 6.0% | E14: — | F14: — | G14: — | H14: — | I14: =('Balance Sheet'!I21-'Balance Sheet'!H21) | J14: =('Balance Sheet'!J21-'Balance Sheet'!I21) | K14: =('Balance Sheet'!K21-'Balance Sheet'!J21) | L14: =('Balance Sheet'!L21-'Balance Sheet'!K21) | M14: =('Balance Sheet'!M21-'Balance Sheet'!L21)
A15: Incr./(decr.) in other current liabilities | B15: OCL 5.5% = FY25 current liabilities minus AP, accrued, and current leases (residual ~594k); not the 45,954 'other' line alone. | C15: LULU balance sheet (10-K) | D15: Ctrl+F "Total current liabilities" 1,887,548 − "Accounts payable" 331,421 − "Accrued liabilities and other" 662,982 − "Current lease liabilities" 298,724 ≈ 594,421 (5.4%) | E15: — | F15: — | G15: — | H15: — | I15: =('Balance Sheet'!I23-'Balance Sheet'!H23) | J15: =('Balance Sheet'!J23-'Balance Sheet'!I23) | K15: =('Balance Sheet'!K23-'Balance Sheet'!J23) | L15: =('Balance Sheet'!L23-'Balance Sheet'!K23) | M15: =('Balance Sheet'!M23-'Balance Sheet'!L23)
A16: Incr./(decr.) in operating lease liab. | B16: Current lease liabilities 2.7% of revenue; short-term portion of operating lease obligations. | C16: LULU lease disclosures (10-K) | D16: Ctrl+F "Current lease liabilities" → 298,724 ÷ "Net revenue" 11,102,600 = 2.7% | E16: — | F16: — | G16: — | H16: — | I16: =('Balance Sheet'!I22-'Balance Sheet'!H22)+('Balance Sheet'!I26-'Balance Sheet'!H26) | J16: =('Balance Sheet'!J22-'Balance Sheet'!I22)+('Balance Sheet'!J26-'Balance Sheet'!I26) | K16: =('Balance Sheet'!K22-'Balance Sheet'!J22)+('Balance Sheet'!K26-'Balance Sheet'!J26) | L16: =('Balance Sheet'!L22-'Balance Sheet'!K22)+('Balance Sheet'!L26-'Balance Sheet'!K26) | M16: =('Balance Sheet'!M22-'Balance Sheet'!L22)+('Balance Sheet'!M26-'Balance Sheet'!L26)
A17: Incr./(decr.) in deferred income taxes | E17: — | F17: — | G17: — | H17: — | I17: =('Balance Sheet'!I27-'Balance Sheet'!H27) | J17: =('Balance Sheet'!J27-'Balance Sheet'!I27) | K17: =('Balance Sheet'!K27-'Balance Sheet'!J27) | L17: =('Balance Sheet'!L27-'Balance Sheet'!K27) | M17: =('Balance Sheet'!M27-'Balance Sheet'!L27)
A18: Incr./(decr.) in other non-current liab. | E18: — | F18: — | G18: — | H18: — | I18: =('Balance Sheet'!I28-'Balance Sheet'!H28) | J18: =('Balance Sheet'!J28-'Balance Sheet'!I28) | K18: =('Balance Sheet'!K28-'Balance Sheet'!J28) | L18: =('Balance Sheet'!L28-'Balance Sheet'!K28) | M18: =('Balance Sheet'!M28-'Balance Sheet'!L28)
A19: Working capital & other (reported, net) | E19: =E20-E5-E6-E7 | F19: =F20-F5-F6-F7 | G19: =G20-G5-G6-G7 | H19: =H20-H5-H6-H7
A20: Net cash from operating activities | E20: 966463 | F20: 2296164 | G20: 2272713 | H20: 1602477 | I20: =I5+I6+I7+SUM(I8:I18) | J20: =J5+J6+J7+SUM(J8:J18) | K20: =K5+K6+K7+SUM(K8:K18) | L20: =L5+L6+L7+SUM(L8:L18) | M20: =M5+M6+M7+SUM(M8:M18)
A22: INVESTING ACTIVITIES
A23: Capital expenditures | B23: FY26 7.0% is $735M / $10.4B, not / FY25 $11.1B. Since 7.0% steps toward FY25 6.1%, we assume a fade: 7.0 / 6.0 / 5.5 / 5.0 / 5.0. | C23: LULU CF statement (10-K) | D23: FY25 actual (10-K) Ctrl+F "680,802" → capex $680.8M Ctrl+F "11,102,600" → sales $11.1B 680.8 / 11,102.6 = 6.1% FY26 capex (10-K) Ctrl+F "$725.0 million and $745.0 million" → mid $735M FY26 sales (earnings) Ctrl+F "$10.350 billion to $10.500 billion" → $10.35–$10.50B (mid $10.425B) 7.0% = $735M / $10.425B ($10B year, not FY25 $11.1B) DCF blend Fade 7.0 / 6.0 / 5.5 / 5.0 / 4.0 5.5% = (7.0+6.0+5.5+5.0+4.0)/5 | E23: -638657 | F23: -651865 | G23: -689232 | H23: -680802 | I23: =-'Income Statement'!I4*'Assumptions'!I14 | J23: =-'Income Statement'!J4*'Assumptions'!J14 | K23: =-'Income Statement'!K4*'Assumptions'!K14 | L23: =-'Income Statement'!L4*'Assumptions'!L14 | M23: =-'Income Statement'!M4*'Assumptions'!M14
A24: Net cash from investing activities | E24: -569937 | F24: -654132 | G24: -798174 | H24: -662118 | I24: =I23 | J24: =J23 | K24: =K23 | L24: =L23 | M24: =M23
A25: (Projections: investing ≈ capex; excl. M&A / securities)
A27: FINANCING ACTIVITIES
A28: Repurchase of common stock | B28: $500M annual repurchases; continued capital return at moderated pace vs FY24–25 peak buyback levels. | C28: LULU CF: share repurchases (10-K) | D28: Ctrl+F "Repurchase of common stock" → ( 1,178,349 ) ($000) FY25; model (500,000)/yr | E28: -444001 | F28: -558652 | G28: -1636879 | H28: -1178349 | I28: =-'Assumptions'!I29 | J28: =-'Assumptions'!J29 | K28: =-'Assumptions'!K29 | L28: =-'Assumptions'!L29 | M28: =-'Assumptions'!M29
A29: Net cash from financing activities | E29: -467487 | F29: -548828 | G29: -1652508 | H29: -1208656 | I29: =I28 | J29: =J28 | K29: =K28 | L29: =L28 | M29: =M28
A30: (Projections: financing ≈ buybacks; SBC non-cash in equity)
A32: Net change in cash | E32: =E20+E24+E29 | F32: =F20+F24+F29 | G32: =G20+G24+G29 | H32: =H20+H24+H29 | I32: =I20+I24+I29 | J32: =J20+J24+J29 | K32: =K20+K24+K29 | L32: =L20+L24+L29 | M32: =M20+M24+M29
A33: Cash, beginning of year | E33: 1150517 | F33: 1154867 | G33: 2243971 | H33: 1984336 | I33: =H34 | J33: =I34 | K33: =J34 | L33: =K34 | M33: =L34
A34: Cash, end of year | E34: 1154867 | F34: 2243971 | G34: 1984336 | H34: 1807202 | I34: =I33+I32 | J34: =J33+J32 | K34: =K33+K32 | L34: =L33+L32 | M34: =M33+M32
