Workbook

Sheet Cover
B2: GLOBAL INVESTMENT SOCIETY | INVESTMENT RESEARCH DIVISION
B4: lululemon athletica inc. (NASDAQ: LULU)
B5: Discounted Cash Flow Valuation — Unlevered Free Cash Flow
B7: Recommendation: LONG / OVERWEIGHT
B9: FONT / COLOR CONVENTION
B10: Blue font = figures reported by the company (click value or source link)
B11: Black font = calculations / formulas
B12: Red font = analyst assumptions (cols B/C on driver tabs)
B14: TABS
B15: WACC • Revenue Drivers • NOPAT Bridge • Scenarios • DCF • Comps / Football Field
B16: ASSUMPTIONS GUIDE (PDF — every tab)
B17: LULU_Assumptions_Memo.pdf — full guide: every red assumption on WACC, Scenarios, Revenue Drivers, NOPAT Bridge, DCF, Comps & 3-Statement .
... B23: Current share price (NASDAQ: LULU)

Sheet WACC
A1: WEIGHTED AVERAGE COST OF CAPITAL
A2: Cost of equity (CAPM) | B2: CAPM: rf + β × ERP | C2: Source (click)
A3: Risk-free rate (10-yr UST) | B3: FRED DGS10 (4.77% → 4.8%) | C3: FRED: 10Y Treasury (DGS10) | D3: 0.048
A4: Equity risk premium | B4: Damodaran implied ERP + 177bps overlay | C4: Damodaran: Historical Implied ERP | D4: 0.06
A5: Tax rate | B5: FY26 Guidance (~30%) | C5: Q2 FY2026 outlook: tax rate ≈ 30% | D5: 0.3
A7: Capital structure (market values)
A8: Share price ($) | B8: NASDAQ Last Sale (~$100) | C8: NASDAQ LULU last sale (current price) | D8: 100
A9: Shares outstanding (000) | B9: FY25 10-K Share Count | C9: LULU FY2025 10-K: shares outstanding | D9: 111380
A10: Market value of equity | B10: NASDAQ Last Sale (~$100) | C10: WACC tab: price × shares | D10: =D8*D9
A11: Operating lease liabilities (ASC 842 debt equiv.) | B11: ASC 842 Lease Debt Equiv. | C11: LULU FY2025 10-K: operating lease liabilities | D11: 1798441
A12: Funded debt (term loans / bonds) | B12: No Term Debt (FY25 10-K) | C12: LULU FY2025 10-K (no funded debt) | D12: 0
A13: Total debt equivalents | C13: https://www.sec.gov/Archives/edgar/data/1397187/000139718726000020/lulu-20260201.htm | D13: =D11+D13
A15: Beta (unlever → relever)
A16: Observed Beta (5Y Monthly) — levered βL | B16: Yahoo βL (5Y Monthly) | C16: Yahoo Finance: LULU Beta (5Y Monthly) | D16: 0.86
A17: Yahoo Total Debt (mrq) | B17: Yahoo MRQ Total Debt | C17: Yahoo Finance: LULU Total Debt (mrq) | D17: 2140000
A18: Yahoo Market Cap (same page as βL) | B18: Price × Shares | C18: Yahoo Finance: LULU Market Cap | D18: 11140000
A19: D/E for unlever (Yahoo debt mrq ÷ Yahoo market cap) | B19: Yahoo MRQ Market Cap | C19: Yahoo Finance: debt (mrq) ÷ market cap | D19: =D18/D19
A20: Yahoo book D/E (mrq) — reference only | B20: Yahoo MRQ Total Debt | C20: Yahoo Finance: Total Debt/Equity (mrq) | D20: 0.4469
A21: Unlevered βu | B21: Hamada Unlever (Yahoo D/E) | C21: WACC tab: Hamada unlever (Yahoo market D/E) | D21: =D17/(1+(1-D5)*D20)
A22: D/E for relever (WACC: FY25 lease debt / market equity) | B22: FY25 Lease Debt / Mkt Cap | C22: WACC tab: FY25 lease debt / market equity | D22: =D14/D10
A23: Sector βu benchmark (Damodaran Special Lines) — not used | B23: Damodaran Benchmark (unused) | C23: Damodaran: US betas by sector (Jan 2026) | D23: 0.95
A24: Beta used (relevered for WACC capital structure) | B24: Relevered β for CAPM | C24: WACC tab: Hamada relever (total D/E incl. leases) | D24: =D22*(1+(1-D5)*D23)
A25: Cost of equity (CAPM)
A26: Cost of equity = rf + β × ERP | D26: =D3+D25*D4
A28: Cost of debt (lease-equivalent)
A29: Pre-tax cost of debt (lease-equivalent) | B29: Lease-Equivalent Borrowing Cost | C29: LULU FY2025 10-K: lease liabilities & no funded debt | D29: 0.05
A30: After-tax cost of debt | D30: =D35*(1-D5)
A32: WACC weights
A33: Equity weight | B33: Mkt Cap / Total Capital | C33: WACC tab: capital structure | D33: =D10/(D10+D14)
A34: Debt weight (leases + funded) | B34: Lease Debt / Total Capital | C34: LULU FY2025 10-K: operating lease liabilities | D34: =D14/(D10+D14)
A35: WACC | C35: https://www.sec.gov/Archives/edgar/data/1397187/000139718726000020/lulu-20260201.htm | D35: =D39*D32+D40*D36
C40: https://www.sec.gov/Archives/edgar/data/1397187/000139718726000020/lulu-20260201.htm

Sheet Scenarios
A1: SCENARIO ANALYSIS
E2: Bear | F2: Base | G2: Bull
A3: Key assumptions (5-yr forecast) | B3: Justification (~20 words) [cols B–D: click + to expand] | C3: Source (click)
A4: FY2026E revenue growth | B4: Q2 FY26 Guidance Midpoint | C4: LULU Q2 FY2026 earnings release | E4: -0.09 | F4: -0.061 | G4: -0.04
A5: FY2027–FY2030E revenue growth (avg) | B5: StockAnalysis 3Y Revenue Forecast | C5: StockAnalysis: LULU 3Y revenue forecast | E5: -0.01 | F5: 0.023 | G5: 0.06
A6: Run-rate EBIT margin (clean, ex-refunds) | B6: Q2 FY26 Run-Rate OM (ex-tariff) | C6: Q2 FY2026 release: 18.8% OM minus 560bps tariffs | E6: 0.12 | F6: 0.132 | G6: 0.145
A7: FY26 IEEPA tariff refunds ($k, already in guide) | B7: FY26 One-Time Tariff Refund | C7: Q2 FY2026 release: $134.5M IEEPA tariff refunds | E7: 134500 | F7: 134500 | G7: 134500
A8: Terminal (FY2030E) EBIT margin | B8: Partial Recovery vs FY25 10-K OM | C8: FY2025 10-K: Operating margin 19.9% (one hit) | E8: 0.12 | F8: 0.155 | G8: 0.19
A9: WACC | B9: Lease-Adjusted CAPM (WACC Tab) | C9: WACC tab: CAPM build | E9: 0.11 | F9: =WACC!D41 | G9: 0.095
A10: Terminal growth | B10: FRED GDPC1 Anchor (~2.1%) | C10: FRED: Real GDP (GDPC1) | E10: 0.015 | F10: 0.0225 | G10: 0.03
A11: Cash tax rate | B11: FY26 Guidance (~30%) | C11: Q2 FY2026 outlook: tax rate ≈ 30% | E11: 0.32 | F11: 0.3 | G11: 0.28
A12: D&A % of revenue | B12: FY25 CF Statement (D&A / Sales) | C12: LULU CF statement (10-K) | E12: 0.045 | F12: 0.045 | G12: 0.045
A13: Capex % of revenue | B13: FY26 Guide Fade to 5.5% Blend | C13: LULU 10-K: 2026 capex guide $725–745M Also: Q2 FY2026 outlook: $10.350B–$10.500B sales | E13: 0.07 | F13: 0.055 | G13: 0.045
A14: Gross margin % | B14: FY25 Reported GM (~56.6%) | C14: LULU FY2025 10-K: Gross profit & COGS | E14: 0.56 | F14: 0.566 | G14: 0.575
A15: DSO (days) — flat vs FY25 | B15: Flat vs FY25 (~6.3 days) | C15: LULU FY2025 10-K: Accounts receivable, net | E15: 6.2678836 | F15: 6.2678836 | G15: 6.2678836
A16: FY25 DIO anchor (days) | B16: FY25 Anchor; −1 Day / Yr | C16: LULU FY2025 10-K: Inventories & COGS | E16: 128.83241 | F16: 128.83241 | G16: 128.83241
A17: DIO decline (days / forecast yr) | B17: FY25 Anchor; −1 Day / Yr | C17: LULU FY2025 10-K: inventory & markdown outlook | E17: 1 | F17: 1 | G17: 1
A18: DPO (days) — flat vs FY25 | B18: Flat vs FY25 (~25 days) | C18: LULU FY2025 10-K: Accounts payable & COGS | E18: 25.105213 | F18: 25.105213 | G18: 25.105213
A19: Prepaid expenses (% of revenue) | B19: FY25 OCA % of Revenue | C19: LULU FY2025 10-K: other current assets (residual) | E19: 0.050806928 | F19: 0.050806928 | G19: 0.050806928
A20: Accrued liabilities (% of revenue) | B20: FY25 Accrued % of Revenue | C20: LULU FY2025 10-K: Accrued liabilities and other | E20: 0.059714121 | F20: 0.059714121 | G20: 0.059714121
A21: Pitch CFF: fixed buyback ($k/yr) bear/base | E21: 500000 | F21: 500000 | G21: 0
A22: Pitch CFF: % of FCF to buybacks (bull) | E22: 0 | F22: 0 | G22: 0.75
A24: 5-year forecast paths (by scenario)
A25: Revenue – year 1 | E25: =11102600*(1+E4) | F25: =11102600*(1+F4) | G25: =11102600*(1+G4)
A26: Revenue – year 2 | E26: =E25*(1+E5) | F26: =F25*(1+F5) | G26: =G25*(1+G5)
A27: Revenue – year 3 | E27: =E26*(1+E5) | F27: =F26*(1+F5) | G27: =G26*(1+G5)
A28: Revenue – year 4 | E28: =E27*(1+E5) | F28: =F27*(1+F5) | G28: =G27*(1+G5)
A29: Revenue – year 5 | E29: =E28*(1+E5) | F29: =F28*(1+F5) | G29: =G28*(1+G5)
A30: Gross margin % – year 1 | E30: =E14 | F30: =F14 | G30: =G14
A31: Gross margin % – year 2 | E31: =E14 | F31: =F14 | G31: =G14
A32: Gross margin % – year 3 | E32: =E14 | F32: =F14 | G32: =G14
A33: Gross margin % – year 4 | E33: =E14 | F33: =F14 | G33: =G14
A34: Gross margin % – year 5 | E34: =E14 | F34: =F14 | G34: =G14
A35: Cost of goods sold (COGS) – year 1 | E35: =E25*(1-E30) | F35: =F25*(1-F30) | G35: =G25*(1-G30)
A36: Cost of goods sold (COGS) – year 2 | E36: =E26*(1-E31) | F36: =F26*(1-F31) | G36: =G26*(1-G31)
A37: Cost of goods sold (COGS) – year 3 | E37: =E27*(1-E32) | F37: =F27*(1-F32) | G37: =G27*(1-G32)
A38: Cost of goods sold (COGS) – year 4 | E38: =E28*(1-E33) | F38: =F28*(1-F33) | G38: =G28*(1-G33)
A39: Cost of goods sold (COGS) – year 5 | E39: =E29*(1-E34) | F39: =F29*(1-F34) | G39: =G29*(1-G34)
A40: Clean EBIT margin – year 1 | E40: =E6+(E8-E6)*0/4 | F40: =F6+(F8-F6)*0/4 | G40: =G6+(G8-G6)*0/4
A41: Clean EBIT margin – year 2 | E41: =E6+(E8-E6)*1/4 | F41: =F6+(F8-F6)*1/4 | G41: =G6+(G8-G6)*1/4
A42: Clean EBIT margin – year 3 | E42: =E6+(E8-E6)*2/4 | F42: =F6+(F8-F6)*2/4 | G42: =G6+(G8-G6)*2/4
A43: Clean EBIT margin – year 4 | E43: =E6+(E8-E6)*3/4 | F43: =F6+(F8-F6)*3/4 | G43: =G6+(G8-G6)*3/4
A44: Clean EBIT margin – year 5 | E44: =E6+(E8-E6)*4/4 | F44: =F6+(F8-F6)*4/4 | G44: =G6+(G8-G6)*4/4
A45: EBIT – year 1 | E45: =E25*E40+E7 | F45: =F25*F40+F7 | G45: =G25*G40+G7
A46: EBIT – year 2 | E46: =E26*E41 | F46: =F26*F41 | G46: =G26*G41
A47: EBIT – year 3 | E47: =E27*E42 | F47: =F27*F42 | G47: =G27*G42
A48: EBIT – year 4 | E48: =E28*E43 | F48: =F28*F43 | G48: =G28*G43
A49: EBIT – year 5 | E49: =E29*E44 | F49: =F29*F44 | G49: =G29*G44
A50: NOPAT – year 1 | E50: =E45*(1-'NOPAT Bridge'!E$39) | F50: ='NOPAT Bridge'!E41 | G50: =G45*(1-'NOPAT Bridge'!E$39)
A51: NOPAT – year 2 | E51: =E46*(1-'NOPAT Bridge'!F$39) | F51: ='NOPAT Bridge'!F41 | G51: =G46*(1-'NOPAT Bridge'!F$39)
A52: NOPAT – year 3 | E52: =E47*(1-'NOPAT Bridge'!G$39) | F52: ='NOPAT Bridge'!G41 | G52: =G47*(1-'NOPAT Bridge'!G$39)
A53: NOPAT – year 4 | E53: =E48*(1-'NOPAT Bridge'!H$39) | F53: ='NOPAT Bridge'!H41 | G53: =G48*(1-'NOPAT Bridge'!H$39)
A54: NOPAT – year 5 | E54: =E49*(1-'NOPAT Bridge'!I$39) | F54: ='NOPAT Bridge'!I41 | G54: =G49*(1-'NOPAT Bridge'!I$39)
A55: D&A – year 1 | E55: =E25*E12 | F55: =F25*F12 | G55: =G25*G12
A56: D&A – year 2 | E56: =E26*E12 | F56: =F26*F12 | G56: =G26*G12
A57: D&A – year 3 | E57: =E27*E12 | F57: =F27*F12 | G57: =G27*G12
A58: D&A – year 4 | E58: =E28*E12 | F58: =F28*F12 | G58: =G28*G12
A59: D&A – year 5 | E59: =E29*E12 | F59: =F29*F12 | G59: =G29*G12
A60: Capex – year 1 | E60: =E25*E13 | F60: =F25*F13 | G60: =G25*G13
A61: Capex – year 2 | E61: =E26*E13 | F61: =F26*F13 | G61: =G26*G13
A62: Capex – year 3 | E62: =E27*E13 | F62: =F27*F13 | G62: =G27*G13
A63: Capex – year 4 | E63: =E28*E13 | F63: =F28*F13 | G63: =G28*G13
A64: Capex – year 5 | E64: =E29*E13 | F64: =F29*F13 | G64: =G29*G13
A65: DSO (days) – year 1 | E65: =E15 | F65: =F15 | G65: =G15
A66: DSO (days) – year 2 | E66: =E15 | F66: =F15 | G66: =G15
A67: DSO (days) – year 3 | E67: =E15 | F67: =F15 | G67: =G15
A68: DSO (days) – year 4 | E68: =E15 | F68: =F15 | G68: =G15
A69: DSO (days) – year 5 | E69: =E15 | F69: =F15 | G69: =G15
A70: Accounts receivable – year 1 | E70: =(E65/365)*E25 | F70: =(F65/365)*F25 | G70: =(G65/365)*G25
A71: Accounts receivable – year 2 | E71: =(E66/365)*E26 | F71: =(F66/365)*F26 | G71: =(G66/365)*G26
A72: Accounts receivable – year 3 | E72: =(E67/365)*E27 | F72: =(F67/365)*F27 | G72: =(G67/365)*G27
A73: Accounts receivable – year 4 | E73: =(E68/365)*E28 | F73: =(F68/365)*F28 | G73: =(G68/365)*G28
A74: Accounts receivable – year 5 | E74: =(E69/365)*E29 | F74: =(F69/365)*F29 | G74: =(G69/365)*G29
A75: DIO (days) – year 1 | E75: =E16-E17*1 | F75: =F16-F17*1 | G75: =G16-G17*1
A76: DIO (days) – year 2 | E76: =E16-E17*2 | F76: =F16-F17*2 | G76: =G16-G17*2
A77: DIO (days) – year 3 | E77: =E16-E17*3 | F77: =F16-F17*3 | G77: =G16-G17*3
A78: DIO (days) – year 4 | E78: =E16-E17*4 | F78: =F16-F17*4 | G78: =G16-G17*4
A79: DIO (days) – year 5 | E79: =E16-E17*5 | F79: =F16-F17*5 | G79: =G16-G17*5
A80: Inventories – year 1 | E80: =(E75/365)*E35 | F80: =(F75/365)*F35 | G80: =(G75/365)*G35
A81: Inventories – year 2 | E81: =(E76/365)*E36 | F81: =(F76/365)*F36 | G81: =(G76/365)*G36
A82: Inventories – year 3 | E82: =(E77/365)*E37 | F82: =(F77/365)*F37 | G82: =(G77/365)*G37
A83: Inventories – year 4 | E83: =(E78/365)*E38 | F83: =(F78/365)*F38 | G83: =(G78/365)*G38
A84: Inventories – year 5 | E84: =(E79/365)*E39 | F84: =(F79/365)*F39 | G84: =(G79/365)*G39
A85: DPO (days) – year 1 | E85: =E18 | F85: =F18 | G85: =G18
A86: DPO (days) – year 2 | E86: =E18 | F86: =F18 | G86: =G18
A87: DPO (days) – year 3 | E87: =E18 | F87: =F18 | G87: =G18
A88: DPO (days) – year 4 | E88: =E18 | F88: =F18 | G88: =G18
A89: DPO (days) – year 5 | E89: =E18 | F89: =F18 | G89: =G18
A90: Accounts payable – year 1 | E90: =(E85/365)*E35 | F90: =(F85/365)*F35 | G90: =(G85/365)*G35
A91: Accounts payable – year 2 | E91: =(E86/365)*E36 | F91: =(F86/365)*F36 | G91: =(G86/365)*G36
A92: Accounts payable – year 3 | E92: =(E87/365)*E37 | F92: =(F87/365)*F37 | G92: =(G87/365)*G37
A93: Accounts payable – year 4 | E93: =(E88/365)*E38 | F93: =(F88/365)*F38 | G93: =(G88/365)*G38
A94: Accounts payable – year 5 | E94: =(E89/365)*E39 | F94: =(F89/365)*F39 | G94: =(G89/365)*G39
A95: Prepaid expenses (other current assets) – year 1 | E95: =E25*E19 | F95: =F25*F19 | G95: =G25*G19
A96: Prepaid expenses (other current assets) – year 2 | E96: =E26*E19 | F96: =F26*F19 | G96: =G26*G19
A97: Prepaid expenses (other current assets) – year 3 | E97: =E27*E19 | F97: =F27*F19 | G97: =G27*G19
A98: Prepaid expenses (other current assets) – year 4 | E98: =E28*E19 | F98: =F28*F19 | G98: =G28*G19
A99: Prepaid expenses (other current assets) – year 5 | E99: =E29*E19 | F99: =F29*F19 | G99: =G29*G19
A100: Accrued liabilities – year 1 | E100: =E25*E20 | F100: =F25*F20 | G100: =G25*G20
A101: Accrued liabilities – year 2 | E101: =E26*E20 | F101: =F26*F20 | G101: =G26*G20
...

Sheet Revenue Drivers
A1: BOTTOM-UP REVENUE DRIVER SCHEDULE (FY2026E–FY2030E)
A2: FY2025A = historical 10-K anchors (blue). FY26–30 = red operational assumptions.
I3: Justification (~20 words)
A4: I. STORE FLEET & SQUARE FOOTAGE (company-operated)
A5: Driver | B5: FY2025A | C5: FY2026E | D5: FY2027E | E5: FY2028E | F5: FY2029E | G5: FY2030E | H5: Units | I5: Justification [cols I–L: click + to expand]
A6: Americas — beginning stores | B6: 462 | C6: =B9 | D6: =C9 | E6: =D9 | F6: =E9 | G6: =F9 | H6: stores | I6: Beginning stores = last year's ending count. Same number, just carried forward into the new fiscal year.
A7: Americas — openings | C7: 8 | D7: 7 | E7: 6 | F7: 5 | G7: 4 | H7: stores | I7: Store openings skew to China (+20 FY26) vs mature Americas (+8). Anchored to FY25 +44 net stores and 11% sq-ft growth. | J7: . FY25 added 44 net stores; model skews openings to China.
A8: Americas — closures | C8: 3 | D8: 3 | E8: 2 | F8: 2 | G8: 2 | H8: stores | I8: Closures assume 2–3 per mature region annually as leases roll; immaterial vs openings in expansion markets. | J8: .
A9: Americas — ending stores | B9: 476 | C9: =C6+C7-C8 | D9: =D6+D7-D8 | E9: =E6+E7-E8 | F9: =F6+F7-F8 | G9: =G6+G7-G8 | H9: stores | I9: Simple roll-forward: where you started, plus openings, minus closures. That's your ending store count for the year.
A10: China Mainland — beginning stores | B10: 151 | C10: =B13 | D10: =C13 | E10: =D13 | F10: =E13 | G10: =F13 | H10: stores | I10: Beginning stores = last year's ending count. Same number, just carried forward into the new fiscal year.
A11: China Mainland — openings | C11: 20 | D11: 18 | E11: 16 | F11: 14 | G11: 12 | H11: stores | I11: Store openings skew to China (+20 FY26) vs mature Americas (+8). Anchored to FY25 +44 net stores and 11% sq-ft growth. | J11: . FY25 added 44 net stores; model skews openings to China.
A12: China Mainland — closures | C12: 1 | D12: 1 | E12: 1 | F12: 1 | G12: 1 | H12: stores | I12: Closures assume 2–3 per mature region annually as leases roll; immaterial vs openings in expansion markets. | J12: .
A13: China Mainland — ending stores | B13: 172 | C13: =C10+C11-C12 | D13: =D10+D11-D12 | E13: =E10+E11-E12 | F13: =F10+F11-F12 | G13: =G10+G11-G12 | H13: stores | I13: Simple roll-forward: where you started, plus openings, minus closures. That's your ending store count for the year.
A14: Rest of World — beginning stores | B14: 154 | C14: =B17 | D14: =C17 | E14: =D17 | F14: =E17 | G14: =F17 | H14: stores | I14: Beginning stores = last year's ending count. Same number, just carried forward into the new fiscal year.
A15: Rest of World — openings | C15: 7 | D15: 6 | E15: 5 | F15: 5 | G15: 4 | H15: stores | I15: Store openings skew to China (+20 FY26) vs mature Americas (+8). Anchored to FY25 +44 net stores and 11% sq-ft growth. | J15: . FY25 added 44 net stores; model skews openings to China.
A16: Rest of World — closures | C16: 2 | D16: 2 | E16: 2 | F16: 2 | G16: 2 | H16: stores | I16: Closures assume 2–3 per mature region annually as leases roll; immaterial vs openings in expansion markets. | J16: .
A17: Rest of World — ending stores | B17: 163 | C17: =C14+C15-C16 | D17: =D14+D15-D16 | E17: =E14+E15-E16 | F17: =F14+F15-F16 | G17: =G14+G15-G16 | H17: stores | I17: Simple roll-forward: where you started, plus openings, minus closures. That's your ending store count for the year.
A18: Total ending stores | B18: 811 | C18: =C9+C13+C17 | D18: =D9+D13+D17 | E18: =E9+E13+E17 | F18: =F9+F13+F17 | G18: =G9+G13+G17 | I18: Add up Americas + China + RoW ending stores. Should tie to the 10-K total company-operated count.
A19: Avg square feet per store | B19: 4366 | C19: 4400 | D19: 4425 | E19: 4450 | F19: 4475 | G19: 4500 | H19: sq ft | I19: 4,367 avg sq ft/store = implied FY25 total sq ft / 811 stores. Modest expansion to 4,500 by FY30. | J19: .54M sq ft / 811 stores ≈ 4,367 sq ft.
A20: Total square footage (end stores × avg sq ft) | B20: =B18*B19 | C20: =C18*C19 | D20: =D18*D19 | E20: =E18*E19 | F20: =F18*F19 | G20: =G18*G19 | H20: sq ft | I20: Ending stores times avg sq ft per box. Gives you total fleet square footage for the productivity math.
A22: II. STORE PRODUCTIVITY (brick & mortar channel)
A23: Driver | B23: FY2025A | C23: FY2026E | D23: FY2027E | E23: FY2028E | F23: FY2029E | G23: FY2030E | H23: Units | I23: Justification [cols I–L: click + to expand]
A24: Sales per square foot ($) | B24: 1426 | C24: 1360 | D24: 1380 | E24: 1400 | F24: 1420 | G24: 1440 | H24: $/sq ft | I24: FY26 SPSF $1,380 reflects Americas traffic/conversion pressure; recovers toward $1,440 by FY30. | J24: .
A25: Americas — comparable sales growth | B25: -0.03 | C25: -0.04 | D25: 0 | E25: 0.01 | F25: 0.02 | G25: 0.02 | H25: % | I25: FY25 Americas comp −3% per 10-K (traffic, conversion, AOV down). FY26 −4%: modest step-down before flat FY27 as promo clears. | J25: . FY26 model −4% before stabilization.
A26: China Mainland — comparable sales growth | B26: 0.2 | C26: 0.14 | D26: 0.12 | E26: 0.1 | F26: 0.08 | G26: 0.07 | H26: % | I26: FY25 China comp +20% (+19% CCY) per 10-K. FY26 +14%: still fastest region but moderating as the store base scales. | J26: . FY26 model +14% on a larger base.
A27: Rest of World — comparable sales growth | B27: 0.09 | C27: 0.07 | D27: 0.06 | E27: 0.05 | F27: 0.04 | G27: 0.04 | H27: % | I27: FY25 RoW comp +9% (+7% CCY) per 10-K. FY26 +7%: hold above CCY, fade to +4% by FY30 as APAC/Europe base matures. | J27: . FY26 model +7%, fading to +4%.
A28: Prior-year store channel revenue ($000) | B28: 5049744 | C28: =B31 | D28: =C31 | E28: =D31 | F28: =E31 | G28: =F31 | H28: $000 | I28: Last year's total store-channel revenue; the base you're growing comps off of, not the new boxes.
A29: Comparable store revenue ($000) | B29: 5049744 | C29: =B28*0.71*(1+C25)+B28*0.16*(1+C26)+B28*0.13*(1+C27) | D29: =C28*0.71*(1+D25)+C28*0.16*(1+D26)+C28*0.13*(1+D27) | E29: =D28*0.71*(1+E25)+D28*0.16*(1+E26)+D28*0.13*(1+E27) | F29: =E28*0.71*(1+F25)+E28*0.16*(1+F26)+E28*0.13*(1+F27) | G29: =F28*0.71*(1+G25)+F28*0.16*(1+G26)+F28*0.13*(1+G27) | I29: Existing-store sales only; prior store rev grown by geo comp %. New doors are a separate line, not in here.
A30: Net new store revenue contribution ($000) | B30: 0 | C30: =(C7-C8+C11-C12+C15-C16)*C19*C24/1000*0.55 | D30: =(D7-D8+D11-D12+D15-D16)*D19*D24/1000*0.55 | E30: =(E7-E8+E11-E12+E15-E16)*E19*E24/1000*0.55 | F30: =(F7-F8+F11-F12+F15-F16)*F19*F24/1000*0.55 | G30: =(G7-G8+G11-G12+G15-G16)*G19*G24/1000*0.55 | I30: Net new doors × sq ft × $/sq ft is plain dollars. /1000 → $000 on this tab. ×0.55 'cause year-one stores don't run full.
A31: Store channel revenue ($000) | B31: 5049744 | C31: =C29+C30 | D31: =D29+D30 | E31: =E29+E30 | F31: =F29+F30 | G31: =G29+G30 | I31: Brick-and-mortar channel = comp store sales plus whatever the net new stores contributed. That's the whole store line.
A33: III. DIRECT-TO-CONSUMER (e-commerce / digital)
A34: Driver | B34: FY2025A | C34: FY2026E | D34: FY2027E | E34: FY2028E | F34: FY2029E | G34: FY2030E | H34: Units | I34: Justification [cols I–L: click + to expand]
A35: Unique digital sessions (millions) | B35: 485 | C35: 485 | D35: 505 | E35: 525 | F35: 545 | G35: 560 | H35: M | I35: 485M FY25 sessions implied from reported e-comm revenue / conv / AOV. FY26 −3% on Americas softness. | J35: . Sessions implied from revenue / conv / AOV.
A36: Digital conversion rate | B36: 0.033 | C36: 0.033 | D36: 0.034 | E36: 0.035 | F36: 0.035 | G36: 0.036 | I36: 3.3% FY26 digital conversion vs 3.5% pressure cited in 10-K Americas; gradual recovery to 3.6%. | J36: . FY26 model 3.3% digital conversion.
A37: Digital average order value ($) | B37: 307 | C37: 305 | D37: 308 | E37: 310 | F37: 312 | G37: 315 | I37: AOV $305 FY26 on promo intensity; steps to $315 by FY30 as mix normalizes. | J37: . FY26 model $305 AOV.
A38: E-commerce revenue ($000) | B38: 4918697 | C38: =C38*1000000*C39*C40/1000 | D38: =D38*1000000*D39*D40/1000 | E38: =E38*1000000*E39*E40/1000 | F38: =F38*1000000*F39*F40/1000 | G38: =G38*1000000*G39*G40/1000 | I38: Traffic × conversion × AOV is dollars. ×1M 'cause sessions are in millions; /1000 puts it in $000 like everything else.
A40: IV. OTHER CHANNELS, GEOGRAPHY & PRODUCT MIX
A41: Driver | B41: FY2025A | C41: FY2026E | D41: FY2027E | E41: FY2028E | F41: FY2029E | G41: FY2030E | H41: Units | I41: Justification [cols I–L: click + to expand]
A42: Other channels (wholesale / license / outlets) ($000) | B42: 1134159 | C42: =B45*(1+-0.02) | D42: =C45*(1+0.0) | E42: =D45*(1+0.02) | F42: =E45*(1+0.02) | G42: =F45*(1+0.02) | H42: $000 | I42: Other channels (wholesale/license/outlets) held at FY25 $1.13B base; low-single-digit growth thereafter. | J42: .13B.
A43: Americas net revenue ($000) | B43: 7847044 | C43: =B46*(C31+C41+C45)/(B31+B41+B45) | D43: =B46*(D31+D41+D45)/(B31+B41+B45) | E43: =B46*(E31+E41+E45)/(B31+B41+B45) | F43: =B46*(F31+F41+F45)/(B31+B41+B45) | G43: =B46*(G31+G41+G45)/(B31+B41+B45) | H43: $000 | I43: Geographic split scales with consolidated growth; FY25 Americas 70.7% of revenue per 10-K segment table. | J43: .7%).
A44: China Mainland net revenue ($000) | B44: 1754799 | C44: =B47*(C31+C41+C45)/(B31+B41+B45) | D44: =B47*(D31+D41+D45)/(B31+B41+B45) | E44: =B47*(E31+E41+E45)/(B31+B41+B45) | F44: =B47*(F31+F41+F45)/(B31+B41+B45) | G44: =B47*(G31+G41+G45)/(B31+B41+B45) | H44: $000 | I44: China 15.8% of FY25 revenue; fastest comp and store growth; expansion market in the driver schedule. | J44: .8%).
A45: Rest of World net revenue ($000) | B45: 1500757 | C45: =B48*(C31+C41+C45)/(B31+B41+B45) | D45: =B48*(D31+D41+D45)/(B31+B41+B45) | E45: =B48*(E31+E41+E45)/(B31+B41+B45) | F45: =B48*(F31+F41+F45)/(B31+B41+B45) | G45: =B48*(G31+G41+G45)/(B31+B41+B45) | H45: $000 | I45: Rest of World 13.5% of FY25 revenue; mid-single-digit comps and steady openings. | J45: .5%).
A46: Women's % of revenue | B46: 0.63 | C46: 0.62 | D46: 0.615 | E46: 0.61 | F46: 0.605 | G46: 0.6 | I46: Women's mix fades 62.5%→60% as men's penetrates; FY25 reported 63% women's per 10-K category disclosure. | J46: .
A47: Men's % of revenue | B47: 0.24 | C47: 0.25 | D47: 0.255 | E47: 0.26 | F47: 0.265 | G47: 0.27 | I47: Men's mix rises 24.5%→27%; FY25 men's grew 4% vs women's 5% per 10-K category commentary. | J47: .
A48: Accessories & other % of revenue | B48: 0.13 | C48: 0.13 | D48: 0.13 | E48: 0.13 | F48: 0.13 | G48: 0.13 | I48: Accessories steady at 13% of revenue; FY25 accessories +8% per 10-K category disclosure. | J48: .
A50: V. CONSOLIDATED REVENUE & RECONCILIATION
A51: Driver | B51: FY2025A | C51: FY2026E | D51: FY2027E | E51: FY2028E | F51: FY2029E | G51: FY2030E | H51: Units | I51: Justification [cols I–L: click + to expand]
A52: Bottom-up total revenue ($000) | B52: 11102600 | C52: =C31+C41+C45 | D52: =D31+D41+D45 | E52: =E31+E41+E45 | F52: =F31+F41+F45 | G52: =G31+G41+G45 | I52: Bottom-up total = store channel + e-comm + other. That's your driver-built revenue before you check Scenarios.
A53: Scenarios base-case revenue ($000) | B53: 11102600 | C53: =Scenarios!F25 | D53: =Scenarios!F26 | E53: =Scenarios!F27 | F53: =Scenarios!F28 | G53: =Scenarios!F29 | I53: Pulls the Scenarios base-case revenue path; that's still the number the DCF actually uses, not the driver total.
A54: Variance (bottom-up − scenarios) ($000) | B54: =B52-B53 | C54: =C52-C53 | D54: =D52-D53 | E54: =E52-E53 | F54: =F52-F53 | G54: =G52-G53 | I54: Driver-built revenue minus Scenarios revenue. Shows you how far off the bottom-up path is from what you're valuing on.
A55: Variance (%) | B55: =IF(B53=0,"",B54/B53) | C55: =IF(C53=0,"",C54/C53) | D55: =IF(D53=0,"",D54/D53) | E55: =IF(E53=0,"",E54/E53) | F55: =IF(F53=0,"",F54/F53) | G55: =IF(G53=0,"",G54/G53) | I55: Variance as a percent of Scenarios revenue. Easy read on whether the driver schedule is close or way out of line.
B56: https://www.sec.gov/Archives/edgar/data/1397187/000139718726000020/lulu-20260201.htm

Sheet NOPAT Bridge
A1: EBIT to NOPAT walk
B2: Justification [cols B–D: click + to expand] | C2: Source (click) | D2: FY2025A | E2: FY2026E | F2: FY2027E | G2: FY2028E | H2: FY2029E | I2: FY2030E
A3: Reported EBIT → Normalized NOPAT (5-phase pipeline)
A6: Driver assumptions
A7: Phase 1: Add back SBC? (0 = no — Convention A: expense stays in EBIT) | B7: SBC Flag (Convention A = 0) | C7: LULU CF statement (10-K): stock-based compensation | D7: 0 | E7: 0 | F7: 0 | G7: 0 | H7: 0 | I7: 0
A8: Convention A: SBC is a real economic cost (captures shareholder dilution). Forecast NOPAT uses Scenarios EBIT with SBC expensed. DCF implied value uses basic shares (111.4M).
A9: Phase 3: Store-channel EBIT margin % | B9: Store EBIT % of Store Rev | C9: FY2025 10-K: company-operated stores net revenue | D9: 0.186 | E9: 0.186 | F9: 0.186 | G9: 0.186 | H9: 0.186 | I9: 0.186
A10: Phase 3: E-commerce EBIT margin % | B10: E-comm EBIT % of E-comm Rev | C10: FY2025 10-K: e-commerce net revenue | D10: 0.236 | E10: 0.236 | F10: 0.236 | G10: 0.236 | H10: 0.236 | I10: 0.236
A11: Phase 3: Other-channels EBIT margin % | B11: Other EBIT % of Other Rev | C11: FY2025 10-K: other channels (residual) | D11: 0.091 | E11: 0.091 | F11: 0.091 | G11: 0.091 | H11: 0.091 | I11: 0.091
A12: Phase 4: Terminal marginal tax rate | B12: Statutory Marginal (30%) | C12: Q2 FY2026 outlook: tax rate ≈ 30% | D12: 0.3 | E12: 0.3 | F12: 0.3 | G12: 0.3 | H12: 0.3 | I12: 0.3
A13: Phase 2: R&D / software amortization period (years) | B13: R&D Capitalization Period | C13: NOPAT Bridge: capitalization convention | D13: 4 | E13: 4 | F13: 4 | G13: 4 | H13: 4 | I13: 4
A15: Phase 1 — Operating normalization
A16: Reported operating income (EBIT) | B16: 10-K EBIT / Scenarios Forecast | C16: LULU FY2025 10-K: Income from operations | D16: 2210615 | E16: =Scenarios!F45 | F16: =Scenarios!F46 | G16: =Scenarios!F47 | H16: =Scenarios!F48 | I16: =Scenarios!F49
A17: + Impairment / intangible amortization (add-back) | B17: Adds back run-rate intangible amortization | C17: LULU FY2025 10-K: amortization of intangible assets | D17: 6961 | E17: 0 | F17: 0 | G17: 0 | H17: 0 | I17: 0
A18: + Restructuring costs (add-back) | B18: Non-Recurring Restructuring Add-Back | C18: LULU FY2025 10-K: restructuring charges | D18: 0 | E18: 0 | F18: 0 | G18: 0 | H18: 0 | I18: 0
A19: + Legal / M&A one-offs (add-back) | B19: One-Off Legal / M&A Strip | C19: LULU FY2025 10-K: SG&A one-offs | D19: 0 | E19: 0 | F19: 0 | G19: 0 | H19: 0 | I19: 0
A20: + Stock-based compensation (add-back only if flag = 1) | B20: SBC Add-Back (if flag = 1) | C20: LULU CF statement (10-K): stock-based compensation | D20: =62203*$D$7 | E20: =Scenarios!F25/11102600*62203*$D$7 | F20: =Scenarios!F26/11102600*62203*$D$7 | G20: =Scenarios!F27/11102600*62203*$D$7 | H20: =Scenarios!F28/11102600*62203*$D$7 | I20: =Scenarios!F29/11102600*62203*$D$7
A21: =Adjusted EBIT (Phase 1) | B21: Phase 1 adjusted EBIT = reported + non-recurring add-backs | C21: NOPAT Bridge tab: Phase 1 subtotal | E21: =E16+E17+E18+E19+E20 | F21: =F16+F17+F18+F19+F20 | G21: =G16+G17+G18+G19+G20 | H21: =H16+H17+H18+H19+H20 | I21: =I16+I17+I18+I19+I20
A22: Phase 2 — Lease & capitalization (ASC 842 / IFRS 16)
A23: + Implied lease interest expense (reclass from rent) | B23: Lease Interest Reclass (memo) | C23: LULU FY2025 10-K: interest on lease liabilities (supplemental) | D23: 1028 | E23: =1028*(Scenarios!F25/11102600) | F23: =1028*(Scenarios!F26/11102600) | G23: =1028*(Scenarios!F27/11102600) | H23: =1028*(Scenarios!F28/11102600) | I23: =1028*(Scenarios!F29/11102600)
A24: + Capitalize R&D / software (current-year expense) | B24: R&D Capitalization (immaterial) | C24: LULU FY2025 10-K: R&D / software expense | D24: 0 | E24: 0 | F24: 0 | G24: 0 | H24: 0 | I24: 0
A25: − Amortization of prior capitalized intangibles | B25: Amortization of prior capitalized intangibles | C25: LULU FY2025 10-K: intangible amortization | D25: 6961 | E25: 0 | F25: 0 | G25: 0 | H25: 0 | I25: 0
A26: =EBIT after lease & capitalization (Phase 2) | B26: Phase 2 EBIT = Phase 1 + lease interest reclass + R&D cap − amortization | C26: NOPAT Bridge tab: Phase 2 subtotal | E26: =E21+E23+E24-E25 | F26: =F21+F23+F24-F25 | G26: =G21+G23+G24-G25 | H26: =H21+H23+H24-H25 | I26: =I21+I23+I24-I25
A27: Phase 3 — Segment / channel EBIT (driver-based)
A28: Store-channel revenue | B28: Not % of revenue; store-channel revenue from Revenue Drivers tab | C28: Revenue Drivers tab: store-channel revenue | D28: 5049744 | E28: ='Revenue Drivers'!F31 | F28: ='Revenue Drivers'!G31 | G28: ='Revenue Drivers'!H31 | H28: ='Revenue Drivers'!I31 | I28: ='Revenue Drivers'!I31
A29: E-commerce revenue | B29: Not % of revenue; e-commerce revenue from Revenue Drivers tab | C29: Revenue Drivers tab: e-commerce revenue | D29: 4918697 | E29: ='Revenue Drivers'!F41 | F29: ='Revenue Drivers'!G41 | G29: ='Revenue Drivers'!H41 | H29: ='Revenue Drivers'!I41 | I29: ='Revenue Drivers'!I41
A30: Other channels revenue | B30: Not % of revenue; wholesale/license/outlet revenue from Revenue Drivers tab | C30: Revenue Drivers tab: other channels revenue | D30: 1134159 | E30: ='Revenue Drivers'!F45 | F30: ='Revenue Drivers'!G45 | G30: ='Revenue Drivers'!H45 | H30: ='Revenue Drivers'!I45 | I30: ='Revenue Drivers'!I45
A31: Store-channel EBIT (= Rev × store margin) | B31: Not % of consolidated revenue; store EBIT ÷ store revenue only (not Scenarios co | C31: FY2025 10-K: company-operated stores net revenue | D31: 939252.38 | E31: =E28*D$9 | F31: =F28*D$9 | G31: =G28*D$9 | H31: =H28*D$9 | I31: =I28*D$9
A32: E-commerce EBIT (= Rev × e-comm margin) | B32: Not % of consolidated revenue; e-commerce EBIT ÷ e-commerce revenue only (not Sc | C32: FY2025 10-K: e-commerce net revenue | D32: 1160812.5 | E32: =E29*D$10 | F32: =F29*D$10 | G32: =G29*D$10 | H32: =H29*D$10 | I32: =I29*D$10
A33: Other-channels EBIT (= Rev × other margin) | B33: Not % of consolidated revenue; other-channel EBIT ÷ other revenue only (not Scen | C33: FY2025 10-K: other channels (residual) | D33: 103208.47 | E33: =E30*D$11 | F33: =F30*D$11 | G33: =G30*D$11 | H33: =H30*D$11 | I33: =I30*D$11
A34: Channel EBIT (sum of sector EBIT) | B34: Phase 3 channel EBIT = Σ sector EBIT_i | C34: NOPAT Bridge tab: sector EBIT subtotal | E34: =E31+E32+E33+Scenarios!F7 | F34: =F31+F32+F33 | G34: =G31+G32+G33 | H34: =H31+H32+H33 | I34: =I31+I32+I33
A35: =EBIT after channel mix (Phase 3) | B35: Channel-mix EBIT output (Phase 3) | C35: NOPAT Bridge tab: Phase 3 subtotal | D35: 2203273.3 | E35: =E34 | F35: =F34 | G35: =G34 | H35: =H34 | I35: =I34
A36: =Normalized EBIT (tax base for NOPAT) | B36: FY25: Phases 1–2 walk-through (SBC not added back; flag = 0) | C36: Scenarios tab: base-case EBIT (forecast) | D36: =D21+D23+D24-D25 | E36: =Scenarios!F45 | F36: =Scenarios!F46 | G36: =Scenarios!F47 | H36: =Scenarios!F48 | I36: =Scenarios!F49
A37: Check vs Scenarios EBIT (base case) | E37: =E36-Scenarios!F45 | F37: =F36-Scenarios!F46 | G37: =G36-Scenarios!F47 | H37: =H36-Scenarios!F48 | I37: =I36-Scenarios!F49
A38: Phase 4 — Tax normalization to NOPAT
A39: Operating effective tax rate (t_operating) | B39: Operating effective tax rate: (tax + interest shield) ÷ (EBT + interest) | C39: LULU FY2025 10-K: income tax & interest expense | D39: 0.29468476 | E39: =0.29468476492135026+(E$12-0.29468476492135026)*1/5 | F39: =0.29468476492135026+(F$12-0.29468476492135026)*2/5 | G39: =0.29468476492135026+(G$12-0.29468476492135026)*3/5 | H39: =0.29468476492135026+(H$12-0.29468476492135026)*4/5 | I39: =0.29468476492135026+(I$12-0.29468476492135026)*5/5
A40: Unlevered tax on normalized EBIT | B40: Unlevered tax = normalized EBIT × t_operating | C40: NOPAT Bridge tab: unlevered tax expense | E40: =E36*E39 | F40: =F36*F39 | G40: =G36*G39 | H40: =H36*H39 | I40: =I36*I39
A41: NORMALIZED NOPAT | B41: NORMALIZED NOPAT = EBIT_norm × (1 − t_operating) | C41: NOPAT Bridge tab: normalized NOPAT | E41: =E36-E40 | F41: =F36-F40 | G41: =G36-G40 | H41: =H36-H40 | I41: =I36-I40

Sheet DCF
A1: DISCOUNTED CASH FLOW — BASE CASE (US$ thousands)
C2: Source (click) | E2: FY2025A | F2: FY2026E | G2: FY2027E | H2: FY2028E | I2: FY2029E | J2: FY2030E | K2: Δ vs Scenarios | L2: Alt. source [cols L–M: click + to expand]
C3: NOPAT Bridge
A4: Net revenue | C4: 'NOPAT Bridge'!A1 | D4: 'Revenue Drivers'!A1 | E4: =Scenarios!F25/(1+Scenarios!$F$4) | F4: =Scenarios!F25 | G4: =Scenarios!F26 | H4: =Scenarios!F27 | I4: =Scenarios!F28 | J4: =Scenarios!F29 | K4: =IF(MAX(ABS(F5-Scenarios!$F$25),ABS(G5-Scenarios!$F$26),ABS(H5-Scenarios!$F$27),ABS(I5-Scenarios!$F$28),ABS(J5-Scenarios!$F$29))<0.5,"OK","CHECK")
A5: Revenue growth % | C5: Q2 FY26 Release | E5: https://www.sec.gov/Archives/edgar/data/1397187/000139718726000020/lulu-20260201.htm | F5: =F5/E5-1 | G5: =G5/F5-1 | H5: =H5/G5-1 | I5: =I5/H5-1 | J5: =J5/I5-1
A6: Gross margin % | C6: 10-K | E6: 0.56600544 | F6: =Scenarios!$F$14 | G6: =Scenarios!$F$14 | H6: =Scenarios!$F$14 | I6: =Scenarios!$F$14 | J6: =Scenarios!$F$14
A7: Cost of goods sold (COGS) | C7: https://www.sec.gov/Archives/edgar/data/1397187/000139718726000020/lulu-20260201.htm | E7: 4818468 | F7: =Scenarios!F35 | G7: =Scenarios!F36 | H7: =Scenarios!F37 | I7: =Scenarios!F38 | J7: =Scenarios!F39 | K7: =IF(MAX(ABS(F8-Scenarios!$F$35),ABS(G8-Scenarios!$F$36),ABS(H8-Scenarios!$F$37),ABS(I8-Scenarios!$F$38),ABS(J8-Scenarios!$F$39))<0.5,"OK","CHECK")
A8: Clean / run-rate EBIT margin % | C8: Q2 FY26 Release | E8: https://www.sec.gov/Archives/edgar/data/1397187/000139718726000020/lulu-20260201.htm | F8: =Scenarios!F40 | G8: =Scenarios!F41 | H8: =Scenarios!F42 | I8: =Scenarios!F43 | J8: =Scenarios!F44 | K8: =IF(MAX(ABS(F9-Scenarios!$F$40),ABS(G9-Scenarios!$F$41),ABS(H9-Scenarios!$F$42),ABS(I9-Scenarios!$F$43),ABS(J9-Scenarios!$F$44))<0.0001,"OK","CHECK")
A9: Plus: FY26 IEEPA tariff refunds (one-time) | C9: Q2 FY26 Release | E9: 0 | F9: =Scenarios!$F$7 | G9: 0 | H9: 0 | I9: 0 | J9: 0
A10: EBIT (incl. FY26 refund) | C10: https://corporate.lululemon.com/newsroom/press-releases/2026/09-03-2026-210528733 | E10: 2210615 | F10: =Scenarios!F45 | G10: =Scenarios!F46 | H10: =Scenarios!F47 | I10: =Scenarios!F48 | J10: =Scenarios!F49 | K10: =IF(MAX(ABS(F11-Scenarios!$F$45),ABS(G11-Scenarios!$F$46),ABS(H11-Scenarios!$F$47),ABS(I11-Scenarios!$F$48),ABS(J11-Scenarios!$F$49))<0.5,"OK","CHECK")
A11: Reported EBIT margin % (incl. FY26 refund) | E11: 0.19910787 | F11: =F11/F5 | G11: =G11/G5 | H11: =H11/H5 | I11: =I11/I5 | J11: =J11/J5
A12: Less: unlevered tax (t_operating from NOPAT Bridge) | E12: https://www.sec.gov/Archives/edgar/data/1397187/000139718726000020/lulu-20260201.htm | F12: =-'NOPAT Bridge'!E40 | G12: =-'NOPAT Bridge'!F40 | H12: =-'NOPAT Bridge'!G40 | I12: =-'NOPAT Bridge'!H40 | J12: =-'NOPAT Bridge'!I40
A13: NOPAT | F13: =Scenarios!F50 | G13: =Scenarios!F51 | H13: =Scenarios!F52 | I13: =Scenarios!F53 | J13: =Scenarios!F54 | K13: =IF(MAX(ABS(F14-Scenarios!$F$50),ABS(G14-Scenarios!$F$51),ABS(H14-Scenarios!$F$52),ABS(I14-Scenarios!$F$53),ABS(J14-Scenarios!$F$54))<0.5,"OK","CHECK")
A14: D&A % of revenue | C14: 10-K | F14: =Scenarios!$F$12 | G14: =Scenarios!$F$12 | H14: =Scenarios!$F$12 | I14: =Scenarios!$F$12 | J14: =Scenarios!$F$12
A15: Plus: depreciation & amortization | C15: https://www.sec.gov/Archives/edgar/data/1397187/000139718726000020/lulu-20260201.htm | F15: =Scenarios!F55 | G15: =Scenarios!F56 | H15: =Scenarios!F57 | I15: =Scenarios!F58 | J15: =Scenarios!F59 | K15: =IF(MAX(ABS(F16-Scenarios!$F$55),ABS(G16-Scenarios!$F$56),ABS(H16-Scenarios!$F$57),ABS(I16-Scenarios!$F$58),ABS(J16-Scenarios!$F$59))<0.5,"OK","CHECK")
A16: Capex % of revenue | C16: 10-K | F16: =Scenarios!$F$13 | G16: =Scenarios!$F$13 | H16: =Scenarios!$F$13 | I16: =Scenarios!$F$13 | J16: =Scenarios!$F$13
A17: Less: capital expenditures | C17: https://www.sec.gov/Archives/edgar/data/1397187/000139718726000020/lulu-20260201.htm | F17: =-Scenarios!F60 | G17: =-Scenarios!F61 | H17: =-Scenarios!F62 | I17: =-Scenarios!F63 | J17: =-Scenarios!F64 | K17: =IF(MAX(ABS(F18+Scenarios!$F$60),ABS(G18+Scenarios!$F$61),ABS(H18+Scenarios!$F$62),ABS(I18+Scenarios!$F$63),ABS(J18+Scenarios!$F$64))<0.5,"OK","CHECK")
A18: DSO (days) — flat vs FY25 | C18: 10-K | E18: 6.2678836 | F18: =Scenarios!F65 | G18: =Scenarios!F66 | H18: =Scenarios!F67 | I18: =Scenarios!F68 | J18: =Scenarios!F69 | K18: =IF(MAX(ABS(F20-Scenarios!$F$65),ABS(G20-Scenarios!$F$66),ABS(H20-Scenarios!$F$67),ABS(I20-Scenarios!$F$68),ABS(J20-Scenarios!$F$69))<0.5,"OK","CHECK")
A19: Accounts receivable, net | C19: 10-K | E19: 190657 | F19: =Scenarios!F70 | G19: =Scenarios!F71 | H19: =Scenarios!F72 | I19: =Scenarios!F73 | J19: =Scenarios!F74 | K19: =IF(MAX(ABS(F21-Scenarios!$F$70),ABS(G21-Scenarios!$F$71),ABS(H21-Scenarios!$F$72),ABS(I21-Scenarios!$F$73),ABS(J21-Scenarios!$F$74))<0.5,"OK","CHECK")
A20: DIO (days) — FY25 anchor, −1 day/yr | C20: 10-K | E20: 128.83241 | F20: =Scenarios!F75 | G20: =Scenarios!F76 | H20: =Scenarios!F77 | I20: =Scenarios!F78 | J20: =Scenarios!F79 | K20: =IF(MAX(ABS(F22-Scenarios!$F$75),ABS(G22-Scenarios!$F$76),ABS(H22-Scenarios!$F$77),ABS(I22-Scenarios!$F$78),ABS(J22-Scenarios!$F$79))<0.5,"OK","CHECK")
A21: Inventories | C21: 10-K | E21: 1700753 | F21: =Scenarios!F80 | G21: =Scenarios!F81 | H21: =Scenarios!F82 | I21: =Scenarios!F83 | J21: =Scenarios!F84 | K21: =IF(MAX(ABS(F23-Scenarios!$F$80),ABS(G23-Scenarios!$F$81),ABS(H23-Scenarios!$F$82),ABS(I23-Scenarios!$F$83),ABS(J23-Scenarios!$F$84))<0.5,"OK","CHECK")
A22: DPO (days) — flat vs FY25 | C22: 10-K | E22: 25.105213 | F22: =Scenarios!F85 | G22: =Scenarios!F86 | H22: =Scenarios!F87 | I22: =Scenarios!F88 | J22: =Scenarios!F89 | K22: =IF(MAX(ABS(F24-Scenarios!$F$85),ABS(G24-Scenarios!$F$86),ABS(H24-Scenarios!$F$87),ABS(I24-Scenarios!$F$88),ABS(J24-Scenarios!$F$89))<0.5,"OK","CHECK")
A23: Accounts payable | C23: 10-K | E23: 331421 | F23: =Scenarios!F90 | G23: =Scenarios!F91 | H23: =Scenarios!F92 | I23: =Scenarios!F93 | J23: =Scenarios!F94 | K23: =IF(MAX(ABS(F25-Scenarios!$F$90),ABS(G25-Scenarios!$F$91),ABS(H25-Scenarios!$F$92),ABS(I25-Scenarios!$F$93),ABS(J25-Scenarios!$F$94))<0.5,"OK","CHECK")
A24: Prepaid expenses (% of revenue) | C24: 10-K | E24: 0.050806928 | F24: =Scenarios!$F$19 | G24: =Scenarios!$F$19 | H24: =Scenarios!$F$19 | I24: =Scenarios!$F$19 | J24: =Scenarios!$F$19
A25: Prepaid expenses (other current assets) | C25: 10-K | E25: 564089 | F25: =Scenarios!F95 | G25: =Scenarios!F96 | H25: =Scenarios!F97 | I25: =Scenarios!F98 | J25: =Scenarios!F99 | K25: =IF(MAX(ABS(F27-Scenarios!$F$95),ABS(G27-Scenarios!$F$96),ABS(H27-Scenarios!$F$97),ABS(I27-Scenarios!$F$98),ABS(J27-Scenarios!$F$99))<0.5,"OK","CHECK")
A26: Accrued liabilities (% of revenue) | C26: 10-K | E26: 0.059714121 | F26: =Scenarios!$F$20 | G26: =Scenarios!$F$20 | H26: =Scenarios!$F$20 | I26: =Scenarios!$F$20 | J26: =Scenarios!$F$20
A27: Accrued liabilities and other | C27: 10-K | E27: 662982 | F27: =Scenarios!F100 | G27: =Scenarios!F101 | H27: =Scenarios!F102 | I27: =Scenarios!F103 | J27: =Scenarios!F104 | K27: =IF(MAX(ABS(F29-Scenarios!$F$100),ABS(G29-Scenarios!$F$101),ABS(H29-Scenarios!$F$102),ABS(I29-Scenarios!$F$103),ABS(J29-Scenarios!$F$104))<0.5,"OK","CHECK")
A28: Current operating assets (AR + inv + prepaids) | C28: Scenarios | E28: https://www.sec.gov/Archives/edgar/data/1397187/000139718726000020/lulu-20260201.htm | F28: =Scenarios!F105 | G28: =Scenarios!F106 | H28: =Scenarios!F107 | I28: =Scenarios!F108 | J28: =Scenarios!F109 | K28: =IF(MAX(ABS(F30-Scenarios!$F$105),ABS(G30-Scenarios!$F$106),ABS(H30-Scenarios!$F$107),ABS(I30-Scenarios!$F$108),ABS(J30-Scenarios!$F$109))<0.5,"OK","CHECK")
A29: Current operating liabilities (AP + accruals) | C29: Scenarios | E29: https://www.sec.gov/Archives/edgar/data/1397187/000139718726000020/lulu-20260201.htm | F29: =Scenarios!F110 | G29: =Scenarios!F111 | H29: =Scenarios!F112 | I29: =Scenarios!F113 | J29: =Scenarios!F114 | K29: =IF(MAX(ABS(F31-Scenarios!$F$110),ABS(G31-Scenarios!$F$111),ABS(H31-Scenarios!$F$112),ABS(I31-Scenarios!$F$113),ABS(J31-Scenarios!$F$114))<0.5,"OK","CHECK")
A30: Net working capital | C30: 10-K | E30: 1461096 | F30: =Scenarios!F115 | G30: =Scenarios!F116 | H30: =Scenarios!F117 | I30: =Scenarios!F118 | J30: =Scenarios!F119 | K30: =IF(MAX(ABS(F32-Scenarios!$F$115),ABS(G32-Scenarios!$F$116),ABS(H32-Scenarios!$F$117),ABS(I32-Scenarios!$F$118),ABS(J32-Scenarios!$F$119))<0.5,"OK","CHECK")
A31: ΔNWC (prior yr − current yr) | C31: Scenarios | F31: =Scenarios!F120 | G31: =Scenarios!F121 | H31: =Scenarios!F122 | I31: =Scenarios!F123 | J31: =Scenarios!F124 | K31: =IF(MAX(ABS(F33-Scenarios!$F$120),ABS(G33-Scenarios!$F$121),ABS(H33-Scenarios!$F$122),ABS(I33-Scenarios!$F$123),ABS(J33-Scenarios!$F$124))<0.5,"OK","CHECK")
A32: Unlevered free cash flow | C32: https://www.sec.gov/Archives/edgar/data/1397187/000139718726000020/lulu-20260201.htm | E32: https://www.sec.gov/Archives/edgar/data/1397187/000139718726000020/lulu-20260201.htm | F32: =Scenarios!F125 | G32: =Scenarios!F126 | H32: =Scenarios!F127 | I32: =Scenarios!F128 | J32: =Scenarios!F129 | K32: =IF(MAX(ABS(F35-Scenarios!$F$125),ABS(G35-Scenarios!$F$126),ABS(H35-Scenarios!$F$127),ABS(I35-Scenarios!$F$128),ABS(J35-Scenarios!$F$129))<0.5,"OK","CHECK")
A33: Discount period (years) | C33: 'Scenarios'!A120 | F33: 1 | G33: 2 | H33: 3 | I33: 4 | J33: 5
A34: Discount factor @ WACC | F34: =1/(1+Scenarios!$F$9)^F36 | G34: =1/(1+Scenarios!$F$9)^G36 | H34: =1/(1+Scenarios!$F$9)^H36 | I34: =1/(1+Scenarios!$F$9)^I36 | J34: =1/(1+Scenarios!$F$9)^J36
A35: PV of unlevered FCF | F35: =F35*F37 | G35: =G35*G37 | H35: =H35*H37 | I35: =I35*I37 | J35: =J35*J37
A37: Scenarios linkage summary (column K should all read OK) | K37: =IF(COUNTIF(K5:K35,"CHECK")=0,"ALL OK","REVIEW")
A38: VALUATION — GORDON GROWTH (PERPETUITY) METHOD
A39: Sum of PV of explicit FCF (FY26–FY30) | E39: =SUM(F38:J38)
A40: Terminal growth rate (g) | C40: FRED | E40: =Scenarios!$F$10
A41: Terminal EBITDA (FY2030E EBIT + D&A) | E41: =J11+J16
A42: Terminal value = FCF₅×(1+g)/(WACC−g) | E42: =J35*(1+Scenarios!$F$10)/(Scenarios!$F$9-Scenarios!$F$10)
A43: Implied exit EV/EBITDA = Gordon TV / FY30 EBITDA | C43: https://fred.stlouisfed.org/series/GDPC1 | E43: =E42/E41
A44: PV of terminal value | E44: =E42/(1+Scenarios!$F$9)^J36
A45: Enterprise value | E45: =E39+E44
A46: Plus: cash & equivalents (FY2025) | C46: 10-K | E46: 1807202
A47: Less: total debt & operating leases | C47: 10-K | E47: -1798441
A48: Equity value | E48: =E45+E46+E47
A49: Shares outstanding (000) | C49: 10-K | E49: 111380
A50: Implied value per share | C50: https://www.sec.gov/Archives/edgar/data/1397187/000139718726000020/lulu-20260201.htm | E50: =E48/E49 | K50: =IF(ABS(E56-Scenarios!$F$132)<0.05,"OK","CHECK")
A51: Current share price | C51: NASDAQ | E51: 100
A52: Implied upside / (downside) | E52: =E50/E51-1
A55: SHARE REPURCHASE & EPS ACCRETION SCHEDULE | C55: https://www.sec.gov/Archives/edgar/data/1397187/000139718726000020/lulu-20260201.htm | E55: https://www.sec.gov/Archives/edgar/data/1397187/000139718726000020/lulu-20260201.htm
A57: Annual repurchase budget ($000) — base case | C57: https://www.nasdaq.com/market-activity/stocks/lulu | E57: 500000 | F57: =$E$65 | G57: =$E$65 | H57: =$E$65 | I57: =$E$65 | J57: =$E$65
A58: Cost of equity — share-price growth rate | E58: 0.105 | F58: =$E$66 | G58: =$E$66 | H58: =$E$66 | I58: =$E$66 | J58: =$E$66
A60: Unlevered free cash flow (from DCF above) | F60: =F35 | G60: =G35 | H60: =H35 | I60: =I35 | J60: =J35
A61: Repurchase cash deployed (= fixed budget) | E61: 0 | F61: =F65 | G61: =G65 | H61: =H65 | I61: =I65 | J61: =J65
A62: Repurchase as % of UFCF (derived) | F62: =F69/F68 | G62: =G69/G68 | H62: =H69/H68 | I62: =I69/I68 | J62: =J69/J68
A64: Projected share price ($) | E64: 100 | F64: =E72*(1+$E$66) | G64: =F72*(1+$E$66) | H64: =G72*(1+$E$66) | I64: =H72*(1+$E$66) | J64: =I72*(1+$E$66)
A65: Shares retired (000) | E65: 0 | F65: =F69/F72 | G65: =G69/G72 | H65: =H69/H72 | I65: =I69/I72 | J65: =J69/J72
A66: Beginning shares (000) | E66: 111380 | F66: =$E$74 | G66: =F75 | H66: =G75 | I66: =H75 | J66: =I75
A67: Ending shares (000) | E67: 111380 | F67: =F74-F73 | G67: =G74-G73 | H67: =H74-H73 | I67: =I74-I73 | J67: =J74-J73
A69: Projected net income ($000) | E69: 1579183 | F69: =('NOPAT Bridge'!E36-'NOPAT Bridge'!E23)*(1-'NOPAT Bridge'!E$39) | G69: =('NOPAT Bridge'!F36-'NOPAT Bridge'!F23)*(1-'NOPAT Bridge'!F$39) | H69: =('NOPAT Bridge'!G36-'NOPAT Bridge'!G23)*(1-'NOPAT Bridge'!G$39) | I69: =('NOPAT Bridge'!H36-'NOPAT Bridge'!H23)*(1-'NOPAT Bridge'!H$39) | J69: =('NOPAT Bridge'!I36-'NOPAT Bridge'!I23)*(1-'NOPAT Bridge'!I$39)
A70: Accretive EPS ($/share) = Net income ÷ ending shares | E70: 14.178335 | F70: =F77/F75 | G70: =G77/G75 | H70: =H77/H75 | I70: =I77/I75 | J70: =J77/J75
A72: CROSS-CHECK — EXIT MULTIPLE METHOD
A73: Exit multiple is the Gordon identity — not a peer pick or an average
A74: Selected exit EV/EBITDA (Gordon implied) | C74: DCF: Gordon implied exit (TV / FY30 EBIT | E74: =E46
A75: Terminal value = Terminal EBITDA × exit multiple | E75: =E41*E74
A76: PV of terminal value | E76: =E75/(1+Scenarios!$F$9)^J36
A77: Enterprise value (exit method) | E77: =E39+E76
A78: Implied value per share (exit method) | E78: =(E77+E46+E47)/E49
A80: TERMINAL VALUE RECONCILIATION (GORDON vs EXIT MULTIPLE)
C81: Exit Multiple
A82: Terminal value ($) | C82: =E83 | M82: 'Comps'!A45
A83: Exit EV/EBITDA (implied vs selected) | C83: =E82
A84: Terminal value variance (%)
A85: Implied share price | C85: =E86
A86: Sanity check: multiples within ±1.5 turns? | C86: =TEXT(D91,"0.0")&"x spread vs Gordon-imp
A89: SENSITIVITY — IMPLIED SHARE PRICE (WACC vs terminal growth)
A90: WACC \ g | C90: FRED | F90: 0.015 | G90: 0.02 | H90: 0.0225 | I90: 0.025 | J90: 0.03 | L90: Scenarios: terminal g
A91: 0.095 | C91: Damodaran | F91: =(NPV(0.095,F35:J35)+(J35*(1+0.015)/(0.095-0.015))/(1+0.095)^5+E46+E47)/E49 | G91: =(NPV(0.095,F35:J35)+(J35*(1+0.02)/(0.095-0.02))/(1+0.095)^5+E46+E47)/E49 | H91: =(NPV(0.095,F35:J35)+(J35*(1+0.0225)/(0.095-0.0225))/(1+0.095)^5+E46+E47)/E49 | I91: =(NPV(0.095,F35:J35)+(J35*(1+0.025)/(0.095-0.025))/(1+0.095)^5+E46+E47)/E49 | J91: =(NPV(0.095,F35:J35)+(J35*(1+0.03)/(0.095-0.03))/(1+0.095)^5+E46+E47)/E49 | L91: WACC tab
A92: 0.1 | F92: =(NPV(0.1,F35:J35)+(J35*(1+0.015)/(0.1-0.015))/(1+0.1)^5+E46+E47)/E49 | G92: =(NPV(0.1,F35:J35)+(J35*(1+0.02)/(0.1-0.02))/(1+0.1)^5+E46+E47)/E49 | H92: =(NPV(0.1,F35:J35)+(J35*(1+0.0225)/(0.1-0.0225))/(1+0.1)^5+E46+E47)/E49 | I92: =(NPV(0.1,F35:J35)+(J35*(1+0.025)/(0.1-0.025))/(1+0.1)^5+E46+E47)/E49 | J92: =(NPV(0.1,F35:J35)+(J35*(1+0.03)/(0.1-0.03))/(1+0.1)^5+E46+E47)/E49 | L92: WACC tab
A93: 0.105 | F93: =(NPV(0.105,F35:J35)+(J35*(1+0.015)/(0.105-0.015))/(1+0.105)^5+E46+E47)/E49 | G93: =(NPV(0.105,F35:J35)+(J35*(1+0.02)/(0.105-0.02))/(1+0.105)^5+E46+E47)/E49 | H93: =(NPV(0.105,F35:J35)+(J35*(1+0.0225)/(0.105-0.0225))/(1+0.105)^5+E46+E47)/E49 | I93: =(NPV(0.105,F35:J35)+(J35*(1+0.025)/(0.105-0.025))/(1+0.105)^5+E46+E47)/E49 | J93: =(NPV(0.105,F35:J35)+(J35*(1+0.03)/(0.105-0.03))/(1+0.105)^5+E46+E47)/E49 | L93: WACC tab
A94: 0.11 | F94: =(NPV(0.11,F35:J35)+(J35*(1+0.015)/(0.11-0.015))/(1+0.11)^5+E46+E47)/E49 | G94: =(NPV(0.11,F35:J35)+(J35*(1+0.02)/(0.11-0.02))/(1+0.11)^5+E46+E47)/E49 | H94: =(NPV(0.11,F35:J35)+(J35*(1+0.0225)/(0.11-0.0225))/(1+0.11)^5+E46+E47)/E49 | I94: =(NPV(0.11,F35:J35)+(J35*(1+0.025)/(0.11-0.025))/(1+0.11)^5+E46+E47)/E49 | J94: =(NPV(0.11,F35:J35)+(J35*(1+0.03)/(0.11-0.03))/(1+0.11)^5+E46+E47)/E49 | L94: WACC tab
A95: 0.115 | F95: =(NPV(0.115,F35:J35)+(J35*(1+0.015)/(0.115-0.015))/(1+0.115)^5+E46+E47)/E49 | G95: =(NPV(0.115,F35:J35)+(J35*(1+0.02)/(0.115-0.02))/(1+0.115)^5+E46+E47)/E49 | H95: =(NPV(0.115,F35:J35)+(J35*(1+0.0225)/(0.115-0.0225))/(1+0.115)^5+E46+E47)/E49 | I95: =(NPV(0.115,F35:J35)+(J35*(1+0.025)/(0.115-0.025))/(1+0.115)^5+E46+E47)/E49 | J95: =(NPV(0.115,F35:J35)+(J35*(1+0.03)/(0.115-0.03))/(1+0.115)^5+E46+E47)/E49 | L95: WACC tab
C96: WACC Tab | L96: FRED: Real GDP (GDPC1)
C98: https://fred.stlouisfed.org/series/GDPC1 | L98: 'Scenarios'!G10
C99: https://www.stern.nyu.edu/~adamodar/New_Home_Page/datafile/histimpl.html | L99: 'WACC'!E41
L100: 'WACC'!E41
L101: 'WACC'!E41
L102: 'WACC'!E41
L103: 'WACC'!E41
C104: 'Scenarios'!G9 | L104: https://fred.stlouisfed.org/series/GDPC1

Sheet Comps
A1: RELATIVE VALUATION — IMPLIED PRICE RANGES (FOOTBALL FIELD)
B2: Justification (~20 words) [cols B–D: click + to expand] | C2: Source (click)
A3: LULU operating metrics (FY2025A / FY2026E)
A4: FY2025A revenue | C4: 10-K | D4: 11102600 | E4: =DCF!E5
A5: FY2025A EBITDA (EBIT + D&A) | D5: =2210615+496228
A6: FY2030E terminal EBITDA (DCF EBIT + D&A) | C6: ↳ DCF base case | D6: =DCF!E44
A7: FY2026E diluted EPS (guidance midpoint) | C7: Release | D7: 9.61 | E7: =Scenarios!F188
A8: Cash & equivalents | C8: 10-K | D8: 1807202 | E8: https://www.sec.gov/Archives/edgar/data/1397187/000139718726000020/lulu-20260201.htm
A9: Shares outstanding (000) | C9: 10-K | D9: 111380 | E9: https://www.sec.gov/Archives/edgar/data/1397187/000139718726000020/lulu-20260201.htm
A10: Current share price | C10: NASDAQ | D10: 100 | E10: https://www.nasdaq.com/market-activity/stocks/lulu
A12: EXIT MULTIPLE BUILD — FY2030E TERMINAL YEAR
A13: Peer / reference EV/EBITDA (forward / illustrative)
A14: PITCHBOOK PUBCOMPS — daily EV / TTM EBITDA as of 04-Sep-2026 ($000)
A15: EV/EBITDA is a black formula (I/J). UAA is shown but excluded from averages (negative TTM EBITDA).
A16: Company | B16: Justification | C16: Source | D16: EV/EBITDA | H16: EV ($000) | I16: EBITDA ($000)
A17: lululemon (LULU) | B17: PitchBook Comps Set 04-Sep-2026. Multiple = daily EV / TTM EBITDA. UAA excluded from the mean (negative EBITDA). | C17: PitchBook Comps Set 04-Sep-2026 | D17: =IF(I19<=0,"n.m.",H19/I19) | H17: 11890440 | I17: 2548084
A18: Under Armour (UAA) | B18: PitchBook Comps Set 04-Sep-2026. Multiple = daily EV / TTM EBITDA. UAA excluded from the mean (negative EBITDA). | C18: PitchBook Comps Set 04-Sep-2026 | D18: =IF(I20<=0,"n.m.",H20/I20) | H18: 3208397 | I18: -23230
A19: adidas (ADS) | B19: PitchBook Comps Set 04-Sep-2026. Multiple = daily EV / TTM EBITDA. UAA excluded from the mean (negative EBITDA). | C19: PitchBook Comps Set 04-Sep-2026 | D19: =IF(I21<=0,"n.m.",H21/I21) | H19: 35661944 | I19: 3857684
A20: Nike (NKE) | B20: PitchBook Comps Set 04-Sep-2026. Multiple = daily EV / TTM EBITDA. UAA excluded from the mean (negative EBITDA). | C20: PitchBook Comps Set 04-Sep-2026 | D20: =IF(I22<=0,"n.m.",H22/I22) | H20: 58972350 | I20: 4647000
A21: Deckers (DECK) | B21: PitchBook Comps Set 04-Sep-2026. Multiple = daily EV / TTM EBITDA. UAA excluded from the mean (negative EBITDA). | C21: PitchBook Comps Set 04-Sep-2026 | D21: =IF(I23<=0,"n.m.",H23/I23) | H21: 10555510 | I21: 1329439
A22: Williams-Sonoma (WSM) | B22: PitchBook Comps Set 04-Sep-2026. Multiple = daily EV / TTM EBITDA. UAA excluded from the mean (negative EBITDA). | C22: PitchBook Comps Set 04-Sep-2026 | D22: =IF(I24<=0,"n.m.",H24/I24) | H22: 27284350 | I22: 1768400
A23: Crocs (CROX) | B23: PitchBook Comps Set 04-Sep-2026. Multiple = daily EV / TTM EBITDA. UAA excluded from the mean (negative EBITDA). | C23: PitchBook Comps Set 04-Sep-2026 | D23: =IF(I25<=0,"n.m.",H25/I25) | H23: 7153911 | I23: 922278
A24: Movado (MOV) | B24: PitchBook Comps Set 04-Sep-2026. Multiple = daily EV / TTM EBITDA. UAA excluded from the mean (negative EBITDA). | C24: PitchBook Comps Set 04-Sep-2026 | D24: =IF(I26<=0,"n.m.",H26/I26) | H24: 616045 | I24: 62010
A25: Levi Strauss (LEVI) | B25: PitchBook Comps Set 04-Sep-2026. Multiple = daily EV / TTM EBITDA. UAA excluded from the mean (negative EBITDA). | C25: PitchBook Comps Set 04-Sep-2026 | D25: =IF(I27<=0,"n.m.",H27/I27) | H25: 9422753 | I25: 976700
A26: La-Z-Boy (LZB) | B26: PitchBook Comps Set 04-Sep-2026. Multiple = daily EV / TTM EBITDA. UAA excluded from the mean (negative EBITDA). | C26: PitchBook Comps Set 04-Sep-2026 | D26: =IF(I28<=0,"n.m.",H28/I28) | H26: 1598873 | I26: 235723
A27: Kontoor (KTB) | B27: PitchBook Comps Set 04-Sep-2026. Multiple = daily EV / TTM EBITDA. UAA excluded from the mean (negative EBITDA). | C27: PitchBook Comps Set 04-Sep-2026 | D27: =IF(I29<=0,"n.m.",H29/I29) | H27: 5236269 | I27: 407521
A30: Averages (live Excel AVERAGE — shown so TV is not a blended print)
A31: Core athletic / apparel mean (LULU / NKE / ADS / DECK / CROX / LEVI / KTB) | B31: PitchBook core set, UAA out. Current tape — not a 2.25% g FY30 exit. | C31: Derived: Excel AVERAGE of the seven core prints | D31: =AVERAGE(D19,D22,D21,D23,D25,D27,D29)
A32: All positive-EBITDA mean (ex-UAA; includes WSM / MOV / LZB) | B32: Wider PitchBook tape. WSM/MOV/LZB are adjacent retail, not athletic. Not the TV. | C32: Derived: Excel AVERAGE of every positive-EBITDA row | D32: =AVERAGE(D19,D21,D22,D23,D24,D25,D26,D27,D28,D29)
A33: We do not average peers for terminal value, and we do not use Alo 5.0x EV/Sales as EV/EBITDA.
A35: Terminal multiple selection (DCF exit method)
A36: Gordon Growth implied exit EV/EBITDA | D36: =DCF!E46
A37: Selected exit multiple (base case) | D37: =DCF!E82
A38: Spread (selected − Gordon implied) | D38: =D45-D44
A39: • Selected exit = Gordon TV / FY30 EBITDA. Identity: (UFCF/EBITDA)×(1+g)/(WACC−g). Live formula, not a typed 8.0x
A40: • At base WACC ~9.0% and g 2.25% that identity is ~7.4x FY30 EBITDA — not a peer average
A41: • PitchBook pubcomps (04-Sep-2026) are the current tape: each multiple is daily EV / TTM EBITDA
A42: • That tape is a check, not the exit. A 2.25% g / 15.5% OM year is not today’s NKE/WSM multiple
A43: • Alo has no EV/EBITDA print. Implied 5.0x is EV/Sales (unclosed $10bn ask / ~$2bn parent sales) — not the FY30 exit
A44: • PitchBook LULU is ~4.7x TTM. Gordon ~7.4x is a partial recovery, not a re-rate to WSM ~15x
A46: Methodology / multiple ranges (FY2030E terminal EBITDA — football field)
A47: Method | B47: Justification | C47: Source | D47: Low mult. | E47: High mult. | F47: Implied px (low) | G47: Implied px (high)
A48: EV / EBITDA (FY2030E terminal) | B48: Lo: 5.0x on FY2030E EBITDA ≈ LULU current trough print. Floor of the range, not the selected exit. Hi: 8.0x = Deckers print as the high end of the range only. Selected exit is Gordon implied, not this cap. | C48: Lo: StockAnalysis: LULU EV/EBITDA Hi: StockAnalysis: DECK EV/EBITDA | D48: 5 | E48: 8 | F48: =(D6*D57+D8)/D9 | G48: =(D6*E57+D8)/D9
A49: DCF exit method (Gordon-implied on FY2030E EBITDA) | B49: Selected exit is Gordon TV / FY30 EBITDA. Identity: (UFCF/EBITDA)×(1+g)/(WACC−g). Not Deckers and not a peer average. | C49: DCF: Gordon implied exit (TV / FY30 EBITDA) | D49: =DCF!E82 | F49: =(D6*D58+D8)/D9
A50: P / E (FY2026E EPS) | B50: Lo: 10x P/E low on FY2026E EPS; trough earnings multiple after guidance reset and sentiment de-rating. Hi: 18x P/E high on FY2026E EPS; modest recovery case still below historical premium LULU multiples. | C50: Lo: StockAnalysis: LULU Forward P/E Hi: StockAnalysis: NKE Forward P/E | D50: 10 | E50: 18 | F50: =D7*D59 | G50: =D7*E59
A51: DCF (bear – bull) | D51: — | E51: — | F51: =Scenarios!E132 | G51: =Scenarios!G132
A53: Current price | C53: NASDAQ | D53: 100
C57: https://stockanalysis.com/stocks/lulu/statistics/
C58: 'DCF'!E82
C59: https://stockanalysis.com/stocks/lulu/statistics/
C62: https://www.nasdaq.com/market-activity/stocks/lulu | E62: https://www.nasdaq.com/market-activity/stocks/lulu
