Workbook

Sheet Cover
B2: lululemon athletica inc. (NASDAQ: LULU)
B4: Unlevered DCF Valuation Model
B5: FY2025A – FY2030E | US$ thousands
B7: Recommendation: LONG / OVERWEIGHT
B9: Tabs: WACC · Scenarios · Revenue Drivers · NOPAT Bridge · DCF · Comps
B19: SOURCES
B20: SEC EDGAR filings, CIK 0001397187 (Form 10-K, FY2025)
B21: FY2025 Form 10-K (ended Feb 1, 2026)
B22: Market data & Q2 FY2026 results (Sep 3, 2026 earnings release)
B23: Current share price (NASDAQ: LULU)

Sheet WACC
A1: WEIGHTED AVERAGE COST OF CAPITAL
A2: Cost of equity (CAPM)
A3: Risk-free rate (10-yr UST) | B3: 0.048
A4: Equity risk premium | B4: 0.06
A5: Tax rate | B5: 0.3
A7: Capital structure (market values)
A8: Share price ($) | B8: 100
A9: Shares outstanding (000) | B9: 111380
A10: Market value of equity | B10: =B8*B9
A11: Operating lease liabilities (ASC 842 debt equiv.) | B11: 1798441
A12: Funded debt (term loans / bonds) | B12: 0
A13: Total debt equivalents | B13: =B11+B12
A15: Beta (unlever → relever)
A16: Observed Beta (5Y Monthly) — levered βL | B16: 0.86
A17: Yahoo Total Debt (mrq) | B17: 2140000
A18: Yahoo Market Cap (same page as βL) | B18: 11140000
A19: D/E for unlever (Yahoo debt mrq ÷ Yahoo market cap) | B19: =B17/B18
A20: Yahoo book D/E (mrq) — reference only | B20: 0.4469
A21: Unlevered βu | B21: =B16/(1+(1-B5)*B19)
A22: D/E for relever (WACC: FY25 lease debt / market equity) | B22: =B13/B10
A23: Sector βu benchmark (Damodaran Special Lines) — not used | B23: 0.95
A24: Beta used (relevered for WACC capital structure) | B24: =B21*(1+(1-B5)*B22)
A26: Cost of equity (CAPM)
A27: Cost of equity = rf + β × ERP | B27: =B3+B24*B4
A29: Cost of debt (lease-equivalent)
A30: Pre-tax cost of debt (lease-equivalent) | B30: 0.05
A31: After-tax cost of debt | B31: =B30*(1-B5)
A33: WACC weights
A34: Equity weight | B34: =B10/(B10+B13)
A35: Debt weight (leases + funded) | B35: =B13/(B10+B13)
A36: WACC | B36: =B34*B27+B35*B31

Sheet Scenarios
A1: SCENARIO ANALYSIS
C2: Bear | D2: Base | E2: Bull
A3: Key assumptions (5-yr forecast)
A4: FY2026E revenue growth | C4: -0.09 | D4: -0.061 | E4: -0.04
A5: FY2027–FY2030E revenue growth (avg) | C5: -0.01 | D5: 0.023 | E5: 0.06
A6: Run-rate EBIT margin (clean, ex-refunds) | C6: 0.12 | D6: 0.132 | E6: 0.145
A7: FY26 IEEPA tariff refunds ($k, already in guide) | C7: 134500 | D7: 134500 | E7: 134500
A8: Terminal (FY2030E) EBIT margin | C8: 0.12 | D8: 0.155 | E8: 0.19
A9: WACC | C9: 0.11 | D9: =WACC!B36 | E9: 0.095
A10: Terminal growth | C10: 0.015 | D10: 0.0225 | E10: 0.03
A11: Cash tax rate | C11: 0.32 | D11: 0.3 | E11: 0.28
A12: D&A % of revenue | C12: 0.045 | D12: 0.045 | E12: 0.045
A13: Capex % of revenue | C13: 0.07 | D13: 0.055 | E13: 0.045
A14: Gross margin % | C14: 0.56 | D14: 0.566 | E14: 0.575
A15: DSO (days) — flat vs FY25 | C15: 6.2678836 | D15: 6.2678836 | E15: 6.2678836
A16: FY25 DIO anchor (days) | C16: 128.83241 | D16: 128.83241 | E16: 128.83241
A17: DIO decline (days / forecast yr) | C17: 1 | D17: 1 | E17: 1
A18: DPO (days) — flat vs FY25 | C18: 25.105213 | D18: 25.105213 | E18: 25.105213
A19: Prepaid expenses (% of revenue) | C19: 0.050806928 | D19: 0.050806928 | E19: 0.050806928
A20: Accrued liabilities (% of revenue) | C20: 0.059714121 | D20: 0.059714121 | E20: 0.059714121
A21: Pitch CFF: fixed buyback ($k/yr) bear/base | C21: 500000 | D21: 500000 | E21: 0
A22: Pitch CFF: % of FCF to buybacks (bull) | C22: 0 | D22: 0 | E22: 0.75
A24: 5-year forecast paths (by scenario)
A25: Revenue – year 1 | C25: =11102600*(1+C4) | D25: =11102600*(1+D4) | E25: =11102600*(1+E4)
A26: Revenue – year 2 | C26: =C25*(1+C5) | D26: =D25*(1+D5) | E26: =E25*(1+E5)
A27: Revenue – year 3 | C27: =C26*(1+C5) | D27: =D26*(1+D5) | E27: =E26*(1+E5)
A28: Revenue – year 4 | C28: =C27*(1+C5) | D28: =D27*(1+D5) | E28: =E27*(1+E5)
A29: Revenue – year 5 | C29: =C28*(1+C5) | D29: =D28*(1+D5) | E29: =E28*(1+E5)
A30: Gross margin % – year 1 | C30: =C14 | D30: =D14 | E30: =E14
A31: Gross margin % – year 2 | C31: =C14 | D31: =D14 | E31: =E14
A32: Gross margin % – year 3 | C32: =C14 | D32: =D14 | E32: =E14
A33: Gross margin % – year 4 | C33: =C14 | D33: =D14 | E33: =E14
A34: Gross margin % – year 5 | C34: =C14 | D34: =D14 | E34: =E14
A35: Cost of goods sold (COGS) – year 1 | C35: =C25*(1-C30) | D35: =D25*(1-D30) | E35: =E25*(1-E30)
A36: Cost of goods sold (COGS) – year 2 | C36: =C26*(1-C31) | D36: =D26*(1-D31) | E36: =E26*(1-E31)
A37: Cost of goods sold (COGS) – year 3 | C37: =C27*(1-C32) | D37: =D27*(1-D32) | E37: =E27*(1-E32)
A38: Cost of goods sold (COGS) – year 4 | C38: =C28*(1-C33) | D38: =D28*(1-D33) | E38: =E28*(1-E33)
A39: Cost of goods sold (COGS) – year 5 | C39: =C29*(1-C34) | D39: =D29*(1-D34) | E39: =E29*(1-E34)
A40: Clean EBIT margin – year 1 | C40: =C6+(C8-C6)*0/4 | D40: =D6+(D8-D6)*0/4 | E40: =E6+(E8-E6)*0/4
A41: Clean EBIT margin – year 2 | C41: =C6+(C8-C6)*1/4 | D41: =D6+(D8-D6)*1/4 | E41: =E6+(E8-E6)*1/4
A42: Clean EBIT margin – year 3 | C42: =C6+(C8-C6)*2/4 | D42: =D6+(D8-D6)*2/4 | E42: =E6+(E8-E6)*2/4
A43: Clean EBIT margin – year 4 | C43: =C6+(C8-C6)*3/4 | D43: =D6+(D8-D6)*3/4 | E43: =E6+(E8-E6)*3/4
A44: Clean EBIT margin – year 5 | C44: =C6+(C8-C6)*4/4 | D44: =D6+(D8-D6)*4/4 | E44: =E6+(E8-E6)*4/4
A45: EBIT – year 1 | C45: =C25*C40+C7 | D45: =D25*D40+D7 | E45: =E25*E40+E7
A46: EBIT – year 2 | C46: =C26*C41 | D46: =D26*D41 | E46: =E26*E41
A47: EBIT – year 3 | C47: =C27*C42 | D47: =D27*D42 | E47: =E27*E42
A48: EBIT – year 4 | C48: =C28*C43 | D48: =D28*D43 | E48: =E28*E43
A49: EBIT – year 5 | C49: =C29*C44 | D49: =D29*D44 | E49: =E29*E44
A50: NOPAT – year 1 | C50: =C45*(1-'NOPAT Bridge'!C$39) | D50: ='NOPAT Bridge'!C41 | E50: =E45*(1-'NOPAT Bridge'!C$39)
A51: NOPAT – year 2 | C51: =C46*(1-'NOPAT Bridge'!D$39) | D51: ='NOPAT Bridge'!D41 | E51: =E46*(1-'NOPAT Bridge'!D$39)
A52: NOPAT – year 3 | C52: =C47*(1-'NOPAT Bridge'!E$39) | D52: ='NOPAT Bridge'!E41 | E52: =E47*(1-'NOPAT Bridge'!E$39)
A53: NOPAT – year 4 | C53: =C48*(1-'NOPAT Bridge'!F$39) | D53: ='NOPAT Bridge'!F41 | E53: =E48*(1-'NOPAT Bridge'!F$39)
A54: NOPAT – year 5 | C54: =C49*(1-'NOPAT Bridge'!G$39) | D54: ='NOPAT Bridge'!G41 | E54: =E49*(1-'NOPAT Bridge'!G$39)
A55: D&A – year 1 | C55: =C25*C12 | D55: =D25*D12 | E55: =E25*E12
A56: D&A – year 2 | C56: =C26*C12 | D56: =D26*D12 | E56: =E26*E12
A57: D&A – year 3 | C57: =C27*C12 | D57: =D27*D12 | E57: =E27*E12
A58: D&A – year 4 | C58: =C28*C12 | D58: =D28*D12 | E58: =E28*E12
A59: D&A – year 5 | C59: =C29*C12 | D59: =D29*D12 | E59: =E29*E12
A60: Capex – year 1 | C60: =C25*C13 | D60: =D25*D13 | E60: =E25*E13
A61: Capex – year 2 | C61: =C26*C13 | D61: =D26*D13 | E61: =E26*E13
A62: Capex – year 3 | C62: =C27*C13 | D62: =D27*D13 | E62: =E27*E13
A63: Capex – year 4 | C63: =C28*C13 | D63: =D28*D13 | E63: =E28*E13
A64: Capex – year 5 | C64: =C29*C13 | D64: =D29*D13 | E64: =E29*E13
A65: DSO (days) – year 1 | C65: =C15 | D65: =D15 | E65: =E15
A66: DSO (days) – year 2 | C66: =C15 | D66: =D15 | E66: =E15
A67: DSO (days) – year 3 | C67: =C15 | D67: =D15 | E67: =E15
A68: DSO (days) – year 4 | C68: =C15 | D68: =D15 | E68: =E15
A69: DSO (days) – year 5 | C69: =C15 | D69: =D15 | E69: =E15
A70: Accounts receivable – year 1 | C70: =(C65/365)*C25 | D70: =(D65/365)*D25 | E70: =(E65/365)*E25
A71: Accounts receivable – year 2 | C71: =(C66/365)*C26 | D71: =(D66/365)*D26 | E71: =(E66/365)*E26
A72: Accounts receivable – year 3 | C72: =(C67/365)*C27 | D72: =(D67/365)*D27 | E72: =(E67/365)*E27
A73: Accounts receivable – year 4 | C73: =(C68/365)*C28 | D73: =(D68/365)*D28 | E73: =(E68/365)*E28
A74: Accounts receivable – year 5 | C74: =(C69/365)*C29 | D74: =(D69/365)*D29 | E74: =(E69/365)*E29
A75: DIO (days) – year 1 | C75: =C16-C17*1 | D75: =D16-D17*1 | E75: =E16-E17*1
A76: DIO (days) – year 2 | C76: =C16-C17*2 | D76: =D16-D17*2 | E76: =E16-E17*2
A77: DIO (days) – year 3 | C77: =C16-C17*3 | D77: =D16-D17*3 | E77: =E16-E17*3
A78: DIO (days) – year 4 | C78: =C16-C17*4 | D78: =D16-D17*4 | E78: =E16-E17*4
A79: DIO (days) – year 5 | C79: =C16-C17*5 | D79: =D16-D17*5 | E79: =E16-E17*5
A80: Inventories – year 1 | C80: =(C75/365)*C35 | D80: =(D75/365)*D35 | E80: =(E75/365)*E35
A81: Inventories – year 2 | C81: =(C76/365)*C36 | D81: =(D76/365)*D36 | E81: =(E76/365)*E36
A82: Inventories – year 3 | C82: =(C77/365)*C37 | D82: =(D77/365)*D37 | E82: =(E77/365)*E37
A83: Inventories – year 4 | C83: =(C78/365)*C38 | D83: =(D78/365)*D38 | E83: =(E78/365)*E38
A84: Inventories – year 5 | C84: =(C79/365)*C39 | D84: =(D79/365)*D39 | E84: =(E79/365)*E39
A85: DPO (days) – year 1 | C85: =C18 | D85: =D18 | E85: =E18
A86: DPO (days) – year 2 | C86: =C18 | D86: =D18 | E86: =E18
A87: DPO (days) – year 3 | C87: =C18 | D87: =D18 | E87: =E18
A88: DPO (days) – year 4 | C88: =C18 | D88: =D18 | E88: =E18
A89: DPO (days) – year 5 | C89: =C18 | D89: =D18 | E89: =E18
A90: Accounts payable – year 1 | C90: =(C85/365)*C35 | D90: =(D85/365)*D35 | E90: =(E85/365)*E35
A91: Accounts payable – year 2 | C91: =(C86/365)*C36 | D91: =(D86/365)*D36 | E91: =(E86/365)*E36
A92: Accounts payable – year 3 | C92: =(C87/365)*C37 | D92: =(D87/365)*D37 | E92: =(E87/365)*E37
A93: Accounts payable – year 4 | C93: =(C88/365)*C38 | D93: =(D88/365)*D38 | E93: =(E88/365)*E38
A94: Accounts payable – year 5 | C94: =(C89/365)*C39 | D94: =(D89/365)*D39 | E94: =(E89/365)*E39
A95: Prepaid expenses (other current assets) – year 1 | C95: =C25*C19 | D95: =D25*D19 | E95: =E25*E19
A96: Prepaid expenses (other current assets) – year 2 | C96: =C26*C19 | D96: =D26*D19 | E96: =E26*E19
A97: Prepaid expenses (other current assets) – year 3 | C97: =C27*C19 | D97: =D27*D19 | E97: =E27*E19
A98: Prepaid expenses (other current assets) – year 4 | C98: =C28*C19 | D98: =D28*D19 | E98: =E28*E19
A99: Prepaid expenses (other current assets) – year 5 | C99: =C29*C19 | D99: =D29*D19 | E99: =E29*E19
A100: Accrued liabilities – year 1 | C100: =C25*C20 | D100: =D25*D20 | E100: =E25*E20
A101: Accrued liabilities – year 2 | C101: =C26*C20 | D101: =D26*D20 | E101: =E26*E20
...

Sheet Revenue Drivers
A1: BOTTOM-UP REVENUE DRIVER SCHEDULE (FY2026E–FY2030E)
A2: FY2025A = FY25 10-K historical anchors (blue). FY26–30 = red operational assumptions. Consolidated revenue cross-checks to Scenarios base case.
A4: I. STORE FLEET & SQUARE FOOTAGE (company-operated)
A5: Driver | B5: FY2025A | C5: FY2026E | D5: FY2027E | E5: FY2028E | F5: FY2029E | G5: FY2030E | H5: Units
A6: Americas — beginning stores | B6: 462 | C6: =B9 | D6: =C9 | E6: =D9 | F6: =E9 | G6: =F9 | H6: stores
A7: Americas — openings | C7: 8 | D7: 7 | E7: 6 | F7: 5 | G7: 4 | H7: stores
A8: Americas — closures | C8: 3 | D8: 3 | E8: 2 | F8: 2 | G8: 2 | H8: stores
A9: Americas — ending stores | B9: 476 | C9: =C6+C7-C8 | D9: =D6+D7-D8 | E9: =E6+E7-E8 | F9: =F6+F7-F8 | G9: =G6+G7-G8 | H9: stores
A10: China Mainland — beginning stores | B10: 151 | C10: =B13 | D10: =C13 | E10: =D13 | F10: =E13 | G10: =F13 | H10: stores
A11: China Mainland — openings | C11: 20 | D11: 18 | E11: 16 | F11: 14 | G11: 12 | H11: stores
A12: China Mainland — closures | C12: 1 | D12: 1 | E12: 1 | F12: 1 | G12: 1 | H12: stores
A13: China Mainland — ending stores | B13: 172 | C13: =C10+C11-C12 | D13: =D10+D11-D12 | E13: =E10+E11-E12 | F13: =F10+F11-F12 | G13: =G10+G11-G12 | H13: stores
A14: Rest of World — beginning stores | B14: 154 | C14: =B17 | D14: =C17 | E14: =D17 | F14: =E17 | G14: =F17 | H14: stores
A15: Rest of World — openings | C15: 7 | D15: 6 | E15: 5 | F15: 5 | G15: 4 | H15: stores
A16: Rest of World — closures | C16: 2 | D16: 2 | E16: 2 | F16: 2 | G16: 2 | H16: stores
A17: Rest of World — ending stores | B17: 163 | C17: =C14+C15-C16 | D17: =D14+D15-D16 | E17: =E14+E15-E16 | F17: =F14+F15-F16 | G17: =G14+G15-G16 | H17: stores
A18: Total ending stores | B18: 811 | C18: =C9+C13+C17 | D18: =D9+D13+D17 | E18: =E9+E13+E17 | F18: =F9+F13+F17 | G18: =G9+G13+G17
A19: Avg square feet per store | B19: 4366 | C19: 4400 | D19: 4425 | E19: 4450 | F19: 4475 | G19: 4500 | H19: sq ft
A20: Total square footage (end stores × avg sq ft) | B20: =B18*B19 | C20: =C18*C19 | D20: =D18*D19 | E20: =E18*E19 | F20: =F18*F19 | G20: =G18*G19 | H20: sq ft
A22: II. STORE PRODUCTIVITY (brick & mortar channel)
A23: Driver | B23: FY2025A | C23: FY2026E | D23: FY2027E | E23: FY2028E | F23: FY2029E | G23: FY2030E | H23: Units
A24: Sales per square foot ($) | B24: 1426 | C24: 1360 | D24: 1380 | E24: 1400 | F24: 1420 | G24: 1440 | H24: $/sq ft
A25: Americas — comparable sales growth | B25: -0.03 | C25: -0.04 | D25: 0 | E25: 0.01 | F25: 0.02 | G25: 0.02 | H25: %
A26: China Mainland — comparable sales growth | B26: 0.2 | C26: 0.14 | D26: 0.12 | E26: 0.1 | F26: 0.08 | G26: 0.07 | H26: %
A27: Rest of World — comparable sales growth | B27: 0.09 | C27: 0.07 | D27: 0.06 | E27: 0.05 | F27: 0.04 | G27: 0.04 | H27: %
A28: Prior-year store channel revenue ($000) | B28: 5049744 | C28: =B31 | D28: =C31 | E28: =D31 | F28: =E31 | G28: =F31 | H28: $000
A29: Comparable store revenue ($000) | B29: 5049744 | C29: =B28*0.71*(1+C25)+B28*0.16*(1+C26)+B28*0.13*(1+C27) | D29: =C28*0.71*(1+D25)+C28*0.16*(1+D26)+C28*0.13*(1+D27) | E29: =D28*0.71*(1+E25)+D28*0.16*(1+E26)+D28*0.13*(1+E27) | F29: =E28*0.71*(1+F25)+E28*0.16*(1+F26)+E28*0.13*(1+F27) | G29: =F28*0.71*(1+G25)+F28*0.16*(1+G26)+F28*0.13*(1+G27)
A30: Net new store revenue contribution ($000) | B30: 0 | C30: =(C7-C8+C11-C12+C15-C16)*C19*C24/1000*0.55 | D30: =(D7-D8+D11-D12+D15-D16)*D19*D24/1000*0.55 | E30: =(E7-E8+E11-E12+E15-E16)*E19*E24/1000*0.55 | F30: =(F7-F8+F11-F12+F15-F16)*F19*F24/1000*0.55 | G30: =(G7-G8+G11-G12+G15-G16)*G19*G24/1000*0.55
A31: Store channel revenue ($000) | B31: 5049744 | C31: =C29+C30 | D31: =D29+D30 | E31: =E29+E30 | F31: =F29+F30 | G31: =G29+G30
A32: fleet traffic (millions of visits) | B32: 42.5 | C32: 40 | D32: 41 | E32: 42 | F32: 43 | G32: 44 | H32: M visits
A33: in-store conversion rate | B33: 0.28 | C33: 0.27 | D33: 0.275 | E33: 0.28 | F33: 0.285 | G33: 0.29
A34: in-store average transaction ($) | B34: 118 | C34: 115 | D34: 116 | E34: 118 | F34: 120 | G34: 122
A36: III. DIRECT-TO-CONSUMER (e-commerce / digital)
A37: Driver | B37: FY2025A | C37: FY2026E | D37: FY2027E | E37: FY2028E | F37: FY2029E | G37: FY2030E | H37: Units
A38: Unique digital sessions (millions) | B38: 485 | C38: 485 | D38: 505 | E38: 525 | F38: 545 | G38: 560 | H38: M
A39: Digital conversion rate | B39: 0.033 | C39: 0.033 | D39: 0.034 | E39: 0.035 | F39: 0.035 | G39: 0.036
A40: Digital average order value ($) | B40: 307 | C40: 305 | D40: 308 | E40: 310 | F40: 312 | G40: 315
A41: E-commerce revenue ($000) | B41: 4918697 | C41: =C38*1000000*C39*C40/1000 | D41: =D38*1000000*D39*D40/1000 | E41: =E38*1000000*E39*E40/1000 | F41: =F38*1000000*F39*F40/1000 | G41: =G38*1000000*G39*G40/1000
A43: IV. OTHER CHANNELS, GEOGRAPHY & PRODUCT MIX
A44: Driver | B44: FY2025A | C44: FY2026E | D44: FY2027E | E44: FY2028E | F44: FY2029E | G44: FY2030E | H44: Units
A45: Other channels (wholesale / license / outlets) ($000) | B45: 1134159 | C45: =B45*(1+-0.02) | D45: =C45*(1+0.0) | E45: =D45*(1+0.02) | F45: =E45*(1+0.02) | G45: =F45*(1+0.02) | H45: $000
A46: Americas net revenue ($000) | B46: 7847044 | C46: =B46*(C31+C41+C45)/(B31+B41+B45) | D46: =B46*(D31+D41+D45)/(B31+B41+B45) | E46: =B46*(E31+E41+E45)/(B31+B41+B45) | F46: =B46*(F31+F41+F45)/(B31+B41+B45) | G46: =B46*(G31+G41+G45)/(B31+B41+B45) | H46: $000
A47: China Mainland net revenue ($000) | B47: 1754799 | C47: =B47*(C31+C41+C45)/(B31+B41+B45) | D47: =B47*(D31+D41+D45)/(B31+B41+B45) | E47: =B47*(E31+E41+E45)/(B31+B41+B45) | F47: =B47*(F31+F41+F45)/(B31+B41+B45) | G47: =B47*(G31+G41+G45)/(B31+B41+B45) | H47: $000
A48: Rest of World net revenue ($000) | B48: 1500757 | C48: =B48*(C31+C41+C45)/(B31+B41+B45) | D48: =B48*(D31+D41+D45)/(B31+B41+B45) | E48: =B48*(E31+E41+E45)/(B31+B41+B45) | F48: =B48*(F31+F41+F45)/(B31+B41+B45) | G48: =B48*(G31+G41+G45)/(B31+B41+B45) | H48: $000
A49: Women's % of revenue | B49: 0.63 | C49: 0.62 | D49: 0.615 | E49: 0.61 | F49: 0.605 | G49: 0.6
A50: Men's % of revenue | B50: 0.24 | C50: 0.25 | D50: 0.255 | E50: 0.26 | F50: 0.265 | G50: 0.27
A51: Accessories & other % of revenue | B51: 0.13 | C51: 0.13 | D51: 0.13 | E51: 0.13 | F51: 0.13 | G51: 0.13
A53: V. CONSOLIDATED REVENUE & RECONCILIATION
A54: Driver | B54: FY2025A | C54: FY2026E | D54: FY2027E | E54: FY2028E | F54: FY2029E | G54: FY2030E | H54: Units
A55: Bottom-up total revenue ($000) | B55: 11102600 | C55: =C31+C41+C45 | D55: =D31+D41+D45 | E55: =E31+E41+E45 | F55: =F31+F41+F45 | G55: =G31+G41+G45
A56: Scenarios base-case revenue ($000) | B56: 11102600 | C56: =Scenarios!D25 | D56: =Scenarios!D26 | E56: =Scenarios!D27 | F56: =Scenarios!D28 | G56: =Scenarios!D29
A57: Variance (bottom-up − scenarios) ($000) | B57: =B55-B56 | C57: =C55-C56 | D57: =D55-D56 | E57: =E55-E56 | F57: =F55-F56 | G57: =G55-G56
A58: Variance (%) | B58: =IF(B56=0,"",B57/B56) | C58: =IF(C56=0,"",C57/C56) | D58: =IF(D56=0,"",D57/D56) | E58: =IF(E56=0,"",E57/E56) | F58: =IF(F56=0,"",F57/F56) | G58: =IF(G56=0,"",G57/G56)
A59: Note: DCF / Scenarios consolidated revenue is the valuation anchor — drivers do not feed the DCF. A small variance vs Scenarios means the bottom-up path still hangs together, so the Scenarios case stays viable. Bigger gaps = revisit drivers or Scenarios assumptions.

Sheet NOPAT Bridge
A1: NOPAT NORMALIZATION PIPELINE (BASE CASE)
B2: FY2025A | C2: FY2026E | D2: FY2027E | E2: FY2028E | F2: FY2029E | G2: FY2030E
A3: Reported EBIT → Normalized NOPAT
A6: Driver assumptions
A7: SBC add-back flag (0 = expensed) | B7: 0 | C7: 0 | D7: 0 | E7: 0 | F7: 0 | G7: 0
A8: Forecast NOPAT uses Scenarios EBIT with SBC expensed. DCF implied value uses basic shares (111.4M).
A9: Store-channel EBIT margin % | B9: 0.186 | C9: 0.186 | D9: 0.186 | E9: 0.186 | F9: 0.186 | G9: 0.186
A10: E-commerce EBIT margin % | B10: 0.236 | C10: 0.236 | D10: 0.236 | E10: 0.236 | F10: 0.236 | G10: 0.236
A11: Other-channels EBIT margin % | B11: 0.091 | C11: 0.091 | D11: 0.091 | E11: 0.091 | F11: 0.091 | G11: 0.091
A12: Terminal marginal tax rate | B12: 0.3 | C12: 0.3 | D12: 0.3 | E12: 0.3 | F12: 0.3 | G12: 0.3
A13: R&D / software amortization period (years) | B13: 4 | C13: 4 | D13: 4 | E13: 4 | F13: 4 | G13: 4
A15: EBIT adjustments
A16: Reported operating income (EBIT) | B16: 2210615 | C16: =Scenarios!D45 | D16: =Scenarios!D46 | E16: =Scenarios!D47 | F16: =Scenarios!D48 | G16: =Scenarios!D49
A17: + Impairment / intangible amortization (add-back) | B17: 6961 | C17: 0 | D17: 0 | E17: 0 | F17: 0 | G17: 0
A18: + Restructuring costs (add-back) | B18: 0 | C18: 0 | D18: 0 | E18: 0 | F18: 0 | G18: 0
A19: + Legal / M&A one-offs (add-back) | B19: 0 | C19: 0 | D19: 0 | E19: 0 | F19: 0 | G19: 0
A20: + Stock-based compensation (add-back only if flag = 1) | B20: =62203*$B$7 | C20: =Scenarios!D25/11102600*62203*$B$7 | D20: =Scenarios!D26/11102600*62203*$B$7 | E20: =Scenarios!D27/11102600*62203*$B$7 | F20: =Scenarios!D28/11102600*62203*$B$7 | G20: =Scenarios!D29/11102600*62203*$B$7
A21: =Adjusted EBIT (Phase 1) | C21: =C16+C17+C18+C19+C20 | D21: =D16+D17+D18+D19+D20 | E21: =E16+E17+E18+E19+E20 | F21: =F16+F17+F18+F19+F20 | G21: =G16+G17+G18+G19+G20
A22: Lease & capitalization
A23: + Implied lease interest expense (reclass from rent) | B23: 1028 | C23: =1028*(Scenarios!D25/11102600) | D23: =1028*(Scenarios!D26/11102600) | E23: =1028*(Scenarios!D27/11102600) | F23: =1028*(Scenarios!D28/11102600) | G23: =1028*(Scenarios!D29/11102600)
A24: + Capitalize R&D / software (current-year expense) | B24: 0 | C24: 0 | D24: 0 | E24: 0 | F24: 0 | G24: 0
A25: − Amortization of prior capitalized intangibles | B25: 6961 | C25: 0 | D25: 0 | E25: 0 | F25: 0 | G25: 0
A26: =EBIT after lease & capitalization (Phase 2) | C26: =C21+C23+C24-C25 | D26: =D21+D23+D24-D25 | E26: =E21+E23+E24-E25 | F26: =F21+F23+F24-F25 | G26: =G21+G23+G24-G25
A27: Segment EBIT bridge
A28: Store-channel revenue | B28: 5049744 | C28: ='Revenue Drivers'!F31 | D28: ='Revenue Drivers'!G31 | E28: ='Revenue Drivers'!H31 | F28: ='Revenue Drivers'!I31 | G28: ='Revenue Drivers'!J31
A29: E-commerce revenue | B29: 4918697 | C29: ='Revenue Drivers'!F41 | D29: ='Revenue Drivers'!G41 | E29: ='Revenue Drivers'!H41 | F29: ='Revenue Drivers'!I41 | G29: ='Revenue Drivers'!J41
A30: Other channels revenue | B30: 1134159 | C30: ='Revenue Drivers'!F45 | D30: ='Revenue Drivers'!G45 | E30: ='Revenue Drivers'!H45 | F30: ='Revenue Drivers'!I45 | G30: ='Revenue Drivers'!J45
A31: Store-channel EBIT (= Rev × store margin) | B31: 939252.38 | C31: =C28*B$9 | D31: =D28*B$9 | E31: =E28*B$9 | F31: =F28*B$9 | G31: =G28*B$9
A32: E-commerce EBIT (= Rev × e-comm margin) | B32: 1160812.5 | C32: =C29*B$10 | D32: =D29*B$10 | E32: =E29*B$10 | F32: =F29*B$10 | G32: =G29*B$10
A33: Other-channels EBIT (= Rev × other margin) | B33: 103208.47 | C33: =C30*B$11 | D33: =D30*B$11 | E33: =E30*B$11 | F33: =F30*B$11 | G33: =G30*B$11
A34: Channel EBIT (sum of sector EBIT) | C34: =C31+C32+C33+Scenarios!D7 | D34: =D31+D32+D33 | E34: =E31+E32+E33 | F34: =F31+F32+F33 | G34: =G31+G32+G33
A35: =EBIT after channel mix (Phase 3) | B35: 2203273.3 | C35: =C34 | D35: =D34 | E35: =E34 | F35: =F34 | G35: =G34
A36: =Normalized EBIT (tax base for NOPAT) | B36: =B21+B23+B24-B25 | C36: =Scenarios!D45 | D36: =Scenarios!D46 | E36: =Scenarios!D47 | F36: =Scenarios!D48 | G36: =Scenarios!D49
A37: Check vs Scenarios EBIT (base case) | C37: =C36-Scenarios!D45 | D37: =D36-Scenarios!D46 | E37: =E36-Scenarios!D47 | F37: =F36-Scenarios!D48 | G37: =G36-Scenarios!D49
A38: Tax normalization
A39: Operating effective tax rate (t_operating) | B39: 0.29468476 | C39: =0.29468476492135026+(C$12-0.29468476492135026)*1/5 | D39: =0.29468476492135026+(D$12-0.29468476492135026)*2/5 | E39: =0.29468476492135026+(E$12-0.29468476492135026)*3/5 | F39: =0.29468476492135026+(F$12-0.29468476492135026)*4/5 | G39: =0.29468476492135026+(G$12-0.29468476492135026)*5/5
A40: Unlevered tax on normalized EBIT | C40: =C36*C39 | D40: =D36*D39 | E40: =E36*E39 | F40: =F36*F39 | G40: =G36*G39
A41: NORMALIZED NOPAT | C41: =C36-C40 | D41: =D36-D40 | E41: =E36-E40 | F41: =F36-F40 | G41: =G36-G40
A43: Reconciliation (execution steps)
C44: Output
A45: 1. Clean base | C45: Adjusted EBIT
A46: 2. Capitalize R&D | C46: EBIT_capitalized
A47: 3. Lease shift | C47: EBIT_lease-adj
A48: 4. Segment mix | C48: Forecast EBIT
A49: 5. NOPAT bridge | C49: Normalized NOPAT
A50: 6. Tariff refund (Scenarios) | C50: Scenarios EBIT (FY26)
A51: Steps 1–4: DCF unchanged on FY26. Step 5 changes NOPAT only (tax). Step 6 changes FY26 EBIT (+ tariff).
A52: Scenarios base-case NOPAT (col G) links to NORMALIZED NOPAT above. Bear/bull apply the same t_operating to their EBIT paths.

Sheet DCF
A1: DISCOUNTED CASH FLOW — BASE CASE (US$ thousands)
B2: FY2025A | C2: FY2026E | D2: FY2027E | E2: FY2028E | F2: FY2029E | G2: FY2030E | H2: Δ vs Scenarios
A3: Forecast drivers linked to Scenarios tab → Base case (column G) | B3: 10-K | H3: (should be 0)
A5: Net revenue | B5: 11102600 | C5: =Scenarios!D25 | D5: =Scenarios!D26 | E5: =Scenarios!D27 | F5: =Scenarios!D28 | G5: =Scenarios!D29 | H5: =IF(MAX(ABS(C5-Scenarios!$D$25),ABS(D5-Scenarios!$D$26),ABS(E5-Scenarios!$D$27),ABS(F5-Scenarios!$D$28),ABS(G5-Scenarios!$D$29))<0.5,"OK","CHECK")
A6: Revenue growth % | C6: =C5/B5-1 | D6: =D5/C5-1 | E6: =E5/D5-1 | F6: =F5/E5-1 | G6: =G5/F5-1
A7: Gross margin % | B7: 0.56600544 | C7: =Scenarios!$D$14 | D7: =Scenarios!$D$14 | E7: =Scenarios!$D$14 | F7: =Scenarios!$D$14 | G7: =Scenarios!$D$14
A8: Cost of goods sold (COGS) | B8: 4818468 | C8: =Scenarios!D35 | D8: =Scenarios!D36 | E8: =Scenarios!D37 | F8: =Scenarios!D38 | G8: =Scenarios!D39 | H8: =IF(MAX(ABS(C8-Scenarios!$D$35),ABS(D8-Scenarios!$D$36),ABS(E8-Scenarios!$D$37),ABS(F8-Scenarios!$D$38),ABS(G8-Scenarios!$D$39))<0.5,"OK","CHECK")
A9: Clean / run-rate EBIT margin % | C9: =Scenarios!D40 | D9: =Scenarios!D41 | E9: =Scenarios!D42 | F9: =Scenarios!D43 | G9: =Scenarios!D44 | H9: =IF(MAX(ABS(C9-Scenarios!$D$40),ABS(D9-Scenarios!$D$41),ABS(E9-Scenarios!$D$42),ABS(F9-Scenarios!$D$43),ABS(G9-Scenarios!$D$44))<0.0001,"OK","CHECK")
A10: Plus: FY26 IEEPA tariff refunds (one-time) | B10: 0 | C10: =Scenarios!$D$7 | D10: 0 | E10: 0 | F10: 0 | G10: 0
A11: EBIT (incl. FY26 refund) | B11: 2210615 | C11: =Scenarios!D45 | D11: =Scenarios!D46 | E11: =Scenarios!D47 | F11: =Scenarios!D48 | G11: =Scenarios!D49 | H11: =IF(MAX(ABS(C11-Scenarios!$D$45),ABS(D11-Scenarios!$D$46),ABS(E11-Scenarios!$D$47),ABS(F11-Scenarios!$D$48),ABS(G11-Scenarios!$D$49))<0.5,"OK","CHECK")
A12: Reported EBIT margin % (incl. FY26 refund) | B12: 0.19910787 | C12: =C11/C5 | D12: =D11/D5 | E12: =E11/E5 | F12: =F11/F5 | G12: =G11/G5
A13: Less: unlevered tax (t_operating from NOPAT Bridge) | C13: =-'NOPAT Bridge'!C40 | D13: =-'NOPAT Bridge'!D40 | E13: =-'NOPAT Bridge'!E40 | F13: =-'NOPAT Bridge'!F40 | G13: =-'NOPAT Bridge'!G40
A14: NOPAT | C14: =Scenarios!D50 | D14: =Scenarios!D51 | E14: =Scenarios!D52 | F14: =Scenarios!D53 | G14: =Scenarios!D54 | H14: =IF(MAX(ABS(C14-Scenarios!$D$50),ABS(D14-Scenarios!$D$51),ABS(E14-Scenarios!$D$52),ABS(F14-Scenarios!$D$53),ABS(G14-Scenarios!$D$54))<0.5,"OK","CHECK")
A15: D&A % of revenue | C15: =Scenarios!$D$12 | D15: =Scenarios!$D$12 | E15: =Scenarios!$D$12 | F15: =Scenarios!$D$12 | G15: =Scenarios!$D$12
A16: Plus: depreciation & amortization | C16: =Scenarios!D55 | D16: =Scenarios!D56 | E16: =Scenarios!D57 | F16: =Scenarios!D58 | G16: =Scenarios!D59 | H16: =IF(MAX(ABS(C16-Scenarios!$D$55),ABS(D16-Scenarios!$D$56),ABS(E16-Scenarios!$D$57),ABS(F16-Scenarios!$D$58),ABS(G16-Scenarios!$D$59))<0.5,"OK","CHECK")
A17: Capex % of revenue | C17: =Scenarios!$D$13 | D17: =Scenarios!$D$13 | E17: =Scenarios!$D$13 | F17: =Scenarios!$D$13 | G17: =Scenarios!$D$13
A18: Less: capital expenditures | C18: =-Scenarios!D60 | D18: =-Scenarios!D61 | E18: =-Scenarios!D62 | F18: =-Scenarios!D63 | G18: =-Scenarios!D64 | H18: =IF(MAX(ABS(C18+Scenarios!$D$60),ABS(D18+Scenarios!$D$61),ABS(E18+Scenarios!$D$62),ABS(F18+Scenarios!$D$63),ABS(G18+Scenarios!$D$64))<0.5,"OK","CHECK")
A19: Working capital schedule (driver-based) [click − to collapse detail]
A20: DSO (days) — flat vs FY25 | B20: 6.2678836 | C20: =Scenarios!D65 | D20: =Scenarios!D66 | E20: =Scenarios!D67 | F20: =Scenarios!D68 | G20: =Scenarios!D69 | H20: =IF(MAX(ABS(C20-Scenarios!$D$65),ABS(D20-Scenarios!$D$66),ABS(E20-Scenarios!$D$67),ABS(F20-Scenarios!$D$68),ABS(G20-Scenarios!$D$69))<0.5,"OK","CHECK")
A21: Accounts receivable, net | B21: 190657 | C21: =Scenarios!D70 | D21: =Scenarios!D71 | E21: =Scenarios!D72 | F21: =Scenarios!D73 | G21: =Scenarios!D74 | H21: =IF(MAX(ABS(C21-Scenarios!$D$70),ABS(D21-Scenarios!$D$71),ABS(E21-Scenarios!$D$72),ABS(F21-Scenarios!$D$73),ABS(G21-Scenarios!$D$74))<0.5,"OK","CHECK")
A22: DIO (days) — FY25 anchor, −1 day/yr | B22: 128.83241 | C22: =Scenarios!D75 | D22: =Scenarios!D76 | E22: =Scenarios!D77 | F22: =Scenarios!D78 | G22: =Scenarios!D79 | H22: =IF(MAX(ABS(C22-Scenarios!$D$75),ABS(D22-Scenarios!$D$76),ABS(E22-Scenarios!$D$77),ABS(F22-Scenarios!$D$78),ABS(G22-Scenarios!$D$79))<0.5,"OK","CHECK")
A23: Inventories | B23: 1700753 | C23: =Scenarios!D80 | D23: =Scenarios!D81 | E23: =Scenarios!D82 | F23: =Scenarios!D83 | G23: =Scenarios!D84 | H23: =IF(MAX(ABS(C23-Scenarios!$D$80),ABS(D23-Scenarios!$D$81),ABS(E23-Scenarios!$D$82),ABS(F23-Scenarios!$D$83),ABS(G23-Scenarios!$D$84))<0.5,"OK","CHECK")
A24: DPO (days) — flat vs FY25 | B24: 25.105213 | C24: =Scenarios!D85 | D24: =Scenarios!D86 | E24: =Scenarios!D87 | F24: =Scenarios!D88 | G24: =Scenarios!D89 | H24: =IF(MAX(ABS(C24-Scenarios!$D$85),ABS(D24-Scenarios!$D$86),ABS(E24-Scenarios!$D$87),ABS(F24-Scenarios!$D$88),ABS(G24-Scenarios!$D$89))<0.5,"OK","CHECK")
A25: Accounts payable | B25: 331421 | C25: =Scenarios!D90 | D25: =Scenarios!D91 | E25: =Scenarios!D92 | F25: =Scenarios!D93 | G25: =Scenarios!D94 | H25: =IF(MAX(ABS(C25-Scenarios!$D$90),ABS(D25-Scenarios!$D$91),ABS(E25-Scenarios!$D$92),ABS(F25-Scenarios!$D$93),ABS(G25-Scenarios!$D$94))<0.5,"OK","CHECK")
A26: Prepaid expenses (% of revenue) | B26: 0.050806928 | C26: =Scenarios!$D$19 | D26: =Scenarios!$D$19 | E26: =Scenarios!$D$19 | F26: =Scenarios!$D$19 | G26: =Scenarios!$D$19
A27: Prepaid expenses (other current assets) | B27: 564089 | C27: =Scenarios!D95 | D27: =Scenarios!D96 | E27: =Scenarios!D97 | F27: =Scenarios!D98 | G27: =Scenarios!D99 | H27: =IF(MAX(ABS(C27-Scenarios!$D$95),ABS(D27-Scenarios!$D$96),ABS(E27-Scenarios!$D$97),ABS(F27-Scenarios!$D$98),ABS(G27-Scenarios!$D$99))<0.5,"OK","CHECK")
A28: Accrued liabilities (% of revenue) | B28: 0.059714121 | C28: =Scenarios!$D$20 | D28: =Scenarios!$D$20 | E28: =Scenarios!$D$20 | F28: =Scenarios!$D$20 | G28: =Scenarios!$D$20
A29: Accrued liabilities and other | B29: 662982 | C29: =Scenarios!D100 | D29: =Scenarios!D101 | E29: =Scenarios!D102 | F29: =Scenarios!D103 | G29: =Scenarios!D104 | H29: =IF(MAX(ABS(C29-Scenarios!$D$100),ABS(D29-Scenarios!$D$101),ABS(E29-Scenarios!$D$102),ABS(F29-Scenarios!$D$103),ABS(G29-Scenarios!$D$104))<0.5,"OK","CHECK")
A30: Current operating assets (AR + inv + prepaids) | C30: =Scenarios!D105 | D30: =Scenarios!D106 | E30: =Scenarios!D107 | F30: =Scenarios!D108 | G30: =Scenarios!D109 | H30: =IF(MAX(ABS(C30-Scenarios!$D$105),ABS(D30-Scenarios!$D$106),ABS(E30-Scenarios!$D$107),ABS(F30-Scenarios!$D$108),ABS(G30-Scenarios!$D$109))<0.5,"OK","CHECK")
A31: Current operating liabilities (AP + accruals) | C31: =Scenarios!D110 | D31: =Scenarios!D111 | E31: =Scenarios!D112 | F31: =Scenarios!D113 | G31: =Scenarios!D114 | H31: =IF(MAX(ABS(C31-Scenarios!$D$110),ABS(D31-Scenarios!$D$111),ABS(E31-Scenarios!$D$112),ABS(F31-Scenarios!$D$113),ABS(G31-Scenarios!$D$114))<0.5,"OK","CHECK")
A32: Net working capital | B32: 1461096 | C32: =Scenarios!D115 | D32: =Scenarios!D116 | E32: =Scenarios!D117 | F32: =Scenarios!D118 | G32: =Scenarios!D119 | H32: =IF(MAX(ABS(C32-Scenarios!$D$115),ABS(D32-Scenarios!$D$116),ABS(E32-Scenarios!$D$117),ABS(F32-Scenarios!$D$118),ABS(G32-Scenarios!$D$119))<0.5,"OK","CHECK")
A33: ΔNWC (prior yr − current yr) | C33: =Scenarios!D120 | D33: =Scenarios!D121 | E33: =Scenarios!D122 | F33: =Scenarios!D123 | G33: =Scenarios!D124 | H33: =IF(MAX(ABS(C33-Scenarios!$D$120),ABS(D33-Scenarios!$D$121),ABS(E33-Scenarios!$D$122),ABS(F33-Scenarios!$D$123),ABS(G33-Scenarios!$D$124))<0.5,"OK","CHECK")
A34: driver-based NWC. ΔNWC = prior-year NWC − current-year NWC; added to UFCF (NWC build = cash outflow).
A35: Unlevered free cash flow | C35: =Scenarios!D125 | D35: =Scenarios!D126 | E35: =Scenarios!D127 | F35: =Scenarios!D128 | G35: =Scenarios!D129 | H35: =IF(MAX(ABS(C35-Scenarios!$D$125),ABS(D35-Scenarios!$D$126),ABS(E35-Scenarios!$D$127),ABS(F35-Scenarios!$D$128),ABS(G35-Scenarios!$D$129))<0.5,"OK","CHECK")
A36: Discount period (years) | C36: 1 | D36: 2 | E36: 3 | F36: 4 | G36: 5
A37: Discount factor @ WACC | C37: =1/(1+Scenarios!$D$9)^C36 | D37: =1/(1+Scenarios!$D$9)^D36 | E37: =1/(1+Scenarios!$D$9)^E36 | F37: =1/(1+Scenarios!$D$9)^F36 | G37: =1/(1+Scenarios!$D$9)^G36
A38: PV of unlevered FCF | C38: =C35*C37 | D38: =D35*D37 | E38: =E35*E37 | F38: =F35*F37 | G38: =G35*G37
A40: Scenarios linkage summary (column K should all read OK) | H40: =IF(COUNTIF(H5:H35,"CHECK")=0,"ALL OK","REVIEW")
A41: VALUATION — GORDON GROWTH (PERPETUITY) METHOD
A42: Sum of PV of explicit FCF (FY26–FY30) | B42: =SUM(C38:G38)
A43: Terminal growth rate (g) | B43: =Scenarios!$D$10
A44: Terminal EBITDA (FY2030E EBIT + D&A) | B44: =G11+G16
A45: Terminal value = FCF₅×(1+g)/(WACC−g) | B45: =G35*(1+Scenarios!$D$10)/(Scenarios!$D$9-Scenarios!$D$10)
A46: Implied exit EV/EBITDA = Gordon TV / FY30 EBITDA | B46: =B45/B44
A47: (UFCF₃₀ / EBITDA₃₀) × (1+g) / (WACC−g) | B47: =G35/B44*(1+Scenarios!$D$10)/(Scenarios!$D$9-Scenarios!$D$10)
A48: PV of terminal value | B48: =B45/(1+Scenarios!$D$9)^G36
A49: Enterprise value | B49: =B42+B48
A50: Plus: cash & equivalents (FY2025) | B50: 1807202
A51: Less: total debt & operating leases | B51: -1798441
A52: funded term debt $0. Operating leases $298,724k current + $1,499,717k non-current = $1,798,441k (ASC 842 debt equivalent).
A53: UFCF is pre-interest; rent stays in opex. We subtract lease liabilities in the bridge but do not add back implied lease interest to EBIT (simplified treatment).
A54: Equity value | B54: =B49+B50+B51
A55: Shares outstanding (000) | B55: 111380
A56: Implied value per share | B56: =B54/B55 | H56: =IF(ABS(B56-Scenarios!$D$132)<0.05,"OK","CHECK")
A57: Current share price | B57: 100
A58: Implied upside / (downside) | B58: =B56/B57-1
A59: % of EV from terminal value | B59: =B48/B49
A62: SHARE REPURCHASE & EPS ACCRETION SCHEDULE
A63: Guardrail: implied value per share above still divides equity value by Day-1 shares (E55 = 111,380k). This schedule does not change intrinsic DCF per share.
A65: Annual repurchase budget ($000) — base case | B65: 500000 | C65: =$B$65 | D65: =$B$65 | E65: =$B$65 | F65: =$B$65 | G65: =$B$65
A66: Cost of equity — share-price growth rate | B66: 0.105 | C66: =$B$66 | D66: =$B$66 | E66: =$B$66 | F66: =$B$66 | G66: =$B$66
A68: Unlevered free cash flow (from DCF above) | C68: =C35 | D68: =D35 | E68: =E35 | F68: =F35 | G68: =G35
A69: Repurchase cash deployed (= fixed budget) | B69: 0 | C69: =C65 | D69: =D65 | E69: =E65 | F69: =F65 | G69: =G65
A70: Repurchase as % of UFCF (derived) | C70: =C69/C68 | D70: =D69/D68 | E70: =E69/E68 | F70: =F69/F68 | G70: =G69/G68
A72: Projected share price ($) | B72: 100 | C72: =B72*(1+$B$66) | D72: =C72*(1+$B$66) | E72: =D72*(1+$B$66) | F72: =E72*(1+$B$66) | G72: =F72*(1+$B$66)
A73: Shares retired (000) | B73: 0 | C73: =C69/C72 | D73: =D69/D72 | E73: =E69/E72 | F73: =F69/F72 | G73: =G69/G72
A74: Beginning shares (000) | B74: 111380 | C74: =$B$74 | D74: =C75 | E74: =D75 | F74: =E75 | G74: =F75
A75: Ending shares (000) | B75: 111380 | C75: =C74-C73 | D75: =D74-D73 | E75: =E74-E73 | F75: =F74-F73 | G75: =G74-G73
A77: Projected net income ($000) | B77: 1579183 | C77: =('NOPAT Bridge'!C36-'NOPAT Bridge'!C23)*(1-'NOPAT Bridge'!C$39) | D77: =('NOPAT Bridge'!D36-'NOPAT Bridge'!D23)*(1-'NOPAT Bridge'!D$39) | E77: =('NOPAT Bridge'!E36-'NOPAT Bridge'!E23)*(1-'NOPAT Bridge'!E$39) | F77: =('NOPAT Bridge'!F36-'NOPAT Bridge'!F23)*(1-'NOPAT Bridge'!F$39) | G77: =('NOPAT Bridge'!G36-'NOPAT Bridge'!G23)*(1-'NOPAT Bridge'!G$39)
A78: Accretive EPS ($/share) = Net income ÷ ending shares | B78: 14.178335 | C78: =C77/C75 | D78: =D77/D75 | E78: =E77/E75 | F78: =F77/F75 | G78: =G77/G75
A80: CROSS-CHECK — EXIT MULTIPLE METHOD
A81: Exit multiple is the Gordon identity — not a peer pick or an average
A82: Selected exit EV/EBITDA (Gordon implied) | B82: =B46
A83: Terminal value = Terminal EBITDA × exit multiple | B83: =B44*B82
A84: PV of terminal value | B84: =B83/(1+Scenarios!$D$9)^G36
A85: Enterprise value (exit method) | B85: =B42+B84
A86: Implied value per share (exit method) | B86: =(B85+B50+B51)/B55
A88: TERMINAL VALUE RECONCILIATION (GORDON vs EXIT MULTIPLE)
A90: Terminal value ($)
A91: Exit EV/EBITDA (implied vs selected)
A92: Terminal value variance (%)
A93: Implied share price
A94: Sanity check: multiples within ±1.5 turns?
A97: SENSITIVITY — IMPLIED SHARE PRICE (WACC vs terminal growth)
A98: WACC \ g | C98: 0.015 | D98: 0.02 | E98: 0.0225 | F98: 0.025 | G98: 0.03
A99: 0.095 | C99: =(NPV(0.095,C35:G35)+(G35*(1+0.015)/(0.095-0.015))/(1+0.095)^5+B50+B51)/B55 | D99: =(NPV(0.095,C35:G35)+(G35*(1+0.02)/(0.095-0.02))/(1+0.095)^5+B50+B51)/B55 | E99: =(NPV(0.095,C35:G35)+(G35*(1+0.0225)/(0.095-0.0225))/(1+0.095)^5+B50+B51)/B55 | F99: =(NPV(0.095,C35:G35)+(G35*(1+0.025)/(0.095-0.025))/(1+0.095)^5+B50+B51)/B55 | G99: =(NPV(0.095,C35:G35)+(G35*(1+0.03)/(0.095-0.03))/(1+0.095)^5+B50+B51)/B55
A100: 0.1 | C100: =(NPV(0.1,C35:G35)+(G35*(1+0.015)/(0.1-0.015))/(1+0.1)^5+B50+B51)/B55 | D100: =(NPV(0.1,C35:G35)+(G35*(1+0.02)/(0.1-0.02))/(1+0.1)^5+B50+B51)/B55 | E100: =(NPV(0.1,C35:G35)+(G35*(1+0.0225)/(0.1-0.0225))/(1+0.1)^5+B50+B51)/B55 | F100: =(NPV(0.1,C35:G35)+(G35*(1+0.025)/(0.1-0.025))/(1+0.1)^5+B50+B51)/B55 | G100: =(NPV(0.1,C35:G35)+(G35*(1+0.03)/(0.1-0.03))/(1+0.1)^5+B50+B51)/B55
A101: 0.105 | C101: =(NPV(0.105,C35:G35)+(G35*(1+0.015)/(0.105-0.015))/(1+0.105)^5+B50+B51)/B55 | D101: =(NPV(0.105,C35:G35)+(G35*(1+0.02)/(0.105-0.02))/(1+0.105)^5+B50+B51)/B55 | E101: =(NPV(0.105,C35:G35)+(G35*(1+0.0225)/(0.105-0.0225))/(1+0.105)^5+B50+B51)/B55 | F101: =(NPV(0.105,C35:G35)+(G35*(1+0.025)/(0.105-0.025))/(1+0.105)^5+B50+B51)/B55 | G101: =(NPV(0.105,C35:G35)+(G35*(1+0.03)/(0.105-0.03))/(1+0.105)^5+B50+B51)/B55
A102: 0.11 | C102: =(NPV(0.11,C35:G35)+(G35*(1+0.015)/(0.11-0.015))/(1+0.11)^5+B50+B51)/B55 | D102: =(NPV(0.11,C35:G35)+(G35*(1+0.02)/(0.11-0.02))/(1+0.11)^5+B50+B51)/B55 | E102: =(NPV(0.11,C35:G35)+(G35*(1+0.0225)/(0.11-0.0225))/(1+0.11)^5+B50+B51)/B55 | F102: =(NPV(0.11,C35:G35)+(G35*(1+0.025)/(0.11-0.025))/(1+0.11)^5+B50+B51)/B55 | G102: =(NPV(0.11,C35:G35)+(G35*(1+0.03)/(0.11-0.03))/(1+0.11)^5+B50+B51)/B55
A103: 0.115 | C103: =(NPV(0.115,C35:G35)+(G35*(1+0.015)/(0.115-0.015))/(1+0.115)^5+B50+B51)/B55 | D103: =(NPV(0.115,C35:G35)+(G35*(1+0.02)/(0.115-0.02))/(1+0.115)^5+B50+B51)/B55 | E103: =(NPV(0.115,C35:G35)+(G35*(1+0.0225)/(0.115-0.0225))/(1+0.115)^5+B50+B51)/B55 | F103: =(NPV(0.115,C35:G35)+(G35*(1+0.025)/(0.115-0.025))/(1+0.115)^5+B50+B51)/B55 | G103: =(NPV(0.115,C35:G35)+(G35*(1+0.03)/(0.115-0.03))/(1+0.115)^5+B50+B51)/B55

Sheet Comps
A1: RELATIVE VALUATION — IMPLIED PRICE RANGES (FOOTBALL FIELD)
A3: LULU operating metrics (FY2025A / FY2026E)
A4: FY2025A revenue | B4: 11102600
A5: FY2025A EBITDA (EBIT + D&A) | B5: =2210615+496228
A6: FY2030E terminal EBITDA (DCF EBIT + D&A) | B6: =DCF!B44
A7: FY2026E diluted EPS (guidance midpoint) | B7: 9.61
A8: Cash & equivalents | B8: 1807202
A9: Shares outstanding (000) | B9: 111380
A10: Current share price | B10: 100
A11: current EV / EBITDA | B11: =(B10*B9-B8)/B5
A12: current P / E (FY2026E) | B12: =B10/B7
A14: EXIT MULTIPLE BUILD — FY2030E TERMINAL YEAR
A15: Peer / reference EV/EBITDA (forward / illustrative)
A16: PITCHBOOK PUBCOMPS — daily EV / TTM EBITDA as of 04-Sep-2026 ($000)
A17: EV/EBITDA is a black formula (I/J). UAA is shown but excluded from averages (negative TTM EBITDA).
A18: Company | B18: EV/EBITDA | F18: EV ($000) | G18: EBITDA ($000)
A19: lululemon (LULU) | B19: =IF(G19<=0,"n.m.",F19/G19) | F19: 11890440 | G19: 2548084
A20: Under Armour (UAA) | B20: =IF(G20<=0,"n.m.",F20/G20) | F20: 3208397 | G20: -23230
A21: adidas (ADS) | B21: =IF(G21<=0,"n.m.",F21/G21) | F21: 35661944 | G21: 3857684
A22: Nike (NKE) | B22: =IF(G22<=0,"n.m.",F22/G22) | F22: 58972350 | G22: 4647000
A23: Deckers (DECK) | B23: =IF(G23<=0,"n.m.",F23/G23) | F23: 10555510 | G23: 1329439
A24: Williams-Sonoma (WSM) | B24: =IF(G24<=0,"n.m.",F24/G24) | F24: 27284350 | G24: 1768400
A25: Crocs (CROX) | B25: =IF(G25<=0,"n.m.",F25/G25) | F25: 7153911 | G25: 922278
A26: Movado (MOV) | B26: =IF(G26<=0,"n.m.",F26/G26) | F26: 616045 | G26: 62010
A27: Levi Strauss (LEVI) | B27: =IF(G27<=0,"n.m.",F27/G27) | F27: 9422753 | G27: 976700
A28: La-Z-Boy (LZB) | B28: =IF(G28<=0,"n.m.",F28/G28) | F28: 1598873 | G28: 235723
A29: Kontoor (KTB) | B29: =IF(G29<=0,"n.m.",F29/G29) | F29: 5236269 | G29: 407521
A31: ALO YOGA BUILD — no source prints EV/EBITDA (Reuters + Forbes)
A32: Column E on the next two rows is $bn, not EV/EBITDA. The black formula is implied EV/Sales on an unclosed ask.
A33: Alo / Color Image 2023 Moelis ask ($bn) | B33: 10
A34: Color Image parent sales, Forbes est. ($bn) | B34: 2
A35: Alo implied EV/Sales (ask / parent sales) | B35: =B33/B34
A36: Alo EV/EBITDA | B36: n.a.
A38: Averages (live Excel AVERAGE — shown so TV is not a blended print)
A39: Core athletic / apparel mean (LULU / NKE / ADS / DECK / CROX / LEVI / KTB) | B39: =AVERAGE(B19,B22,B21,B23,B25,B27,B29)
A40: All positive-EBITDA mean (ex-UAA; includes WSM / MOV / LZB) | B40: =AVERAGE(B19,B21,B22,B23,B24,B25,B26,B27,B28,B29)
A41: We do not average peers for terminal value, and we do not use Alo 5.0x EV/Sales as EV/EBITDA.
A43: Terminal multiple selection (DCF exit method)
A44: Gordon Growth implied exit EV/EBITDA | B44: =DCF!B46
A45: Selected exit multiple (base case) | B45: =DCF!B82
A46: Spread (selected − Gordon implied) | B46: =B45-B44
A47: Rationale for selected exit (Gordon identity, not a peer pick)
A48: • Selected exit = Gordon TV / FY30 EBITDA. Identity: (UFCF/EBITDA)×(1+g)/(WACC−g). Live formula, not a typed 8.0x
A49: • At base WACC ~9.0% and g 2.25% that identity is ~7.4x FY30 EBITDA — not a peer average
A50: • PitchBook pubcomps (04-Sep-2026) are the current tape: each multiple is daily EV / TTM EBITDA
A51: • That tape is a check, not the exit. A 2.25% g / 15.5% OM year is not today’s NKE/WSM multiple
A52: • Alo has no EV/EBITDA print. Implied 5.0x is EV/Sales (unclosed $10bn ask / ~$2bn parent sales) — not the FY30 exit
A53: • PitchBook LULU is ~4.7x TTM. Gordon ~7.4x is a partial recovery, not a re-rate to WSM ~15x
A55: Methodology / multiple ranges (FY2030E terminal EBITDA — football field)
A56: Method | B56: Low mult. | C56: High mult. | D56: Implied px (low) | E56: Implied px (high)
A57: EV / EBITDA (FY2030E terminal) | B57: 5 | C57: 8 | D57: =(B6*B57+B8)/B9 | E57: =(B6*C57+B8)/B9
A58: DCF exit method (Gordon-implied on FY2030E EBITDA) | B58: =DCF!B82 | D58: =(B6*B58+B8)/B9
A59: P / E (FY2026E EPS) | B59: 10 | C59: 18 | D59: =B7*B59 | E59: =B7*C59
A60: DCF (bear – bull) | B60: — | C60: — | D60: =Scenarios!C132 | E60: =Scenarios!E132
A62: Current price | B62: 100
A63: Note: pubcomps are PitchBook 04-Sep-2026 (EV/EBITDA = daily EV / TTM EBITDA). UAA excluded from the mean. Selected TV is Gordon implied, not the PitchBook average. Alo EV/EBITDA is n.a.
